{
  "26,-270": {
    "SourceVersionHash": "I8aToo+SQcdBh2GHRwH3xqeuTxY=",
    "VersionHash": "oob4lno7z3G1DuB/t2qY+ih94sE="
  },
  "25,-270": {
    "SourceVersionHash": "I8aToo+SQcdBh2GHRwH3xqeuTxY=",
    "VersionHash": "oob4lno7z3G1DuB/t2qY+ih94sE="
  },
  "27,-270": {
    "SourceVersionHash": "I8aToo+SQcdBh2GHRwH3xqeuTxY=",
    "VersionHash": "oob4lno7z3G1DuB/t2qY+ih94sE="
  },
  "24,-270": {
    "SourceVersionHash": "I8aToo+SQcdBh2GHRwH3xqeuTxY=",
    "VersionHash": "oob4lno7z3G1DuB/t2qY+ih94sE="
  },
  "28,-270": {
    "SourceVersionHash": "I8aToo+SQcdBh2GHRwH3xqeuTxY=",
    "VersionHash": "oob4lno7z3G1DuB/t2qY+ih94sE="
  },
  "27,-269": {
    "SourceVersionHash": "I8aToo+SQcdBh2GHRwH3xqeuTxY=",
    "VersionHash": "oob4lno7z3G1DuB/t2qY+ih94sE="
  },
  "24,-269": {
    "SourceVersionHash": "I8aToo+SQcdBh2GHRwH3xqeuTxY=",
    "VersionHash": "oob4lno7z3G1DuB/t2qY+ih94sE="
  },
  "29,-270": {
    "SourceVersionHash": "I8aToo+SQcdBh2GHRwH3xqeuTxY=",
    "VersionHash": "oob4lno7z3G1DuB/t2qY+ih94sE="
  },
  "26,-269": {
    "SourceVersionHash": "I8aToo+SQcdBh2GHRwH3xqeuTxY=",
    "VersionHash": "oob4lno7z3G1DuB/t2qY+ih94sE="
  },
  "25,-269": {
    "SourceVersionHash": "I8aToo+SQcdBh2GHRwH3xqeuTxY=",
    "VersionHash": "oob4lno7z3G1DuB/t2qY+ih94sE="
  },
  "28,-269": {
    "SourceVersionHash": "I8aToo+SQcdBh2GHRwH3xqeuTxY=",
    "VersionHash": "oob4lno7z3G1DuB/t2qY+ih94sE="
  },
  "29,-269": {
    "SourceVersionHash": "I8aToo+SQcdBh2GHRwH3xqeuTxY=",
    "VersionHash": "oob4lno7z3G1DuB/t2qY+ih94sE="
  },
  "26,-268": {
    "SourceVersionHash": "I8aToo+SQcdBh2GHRwH3xqeuTxY=",
    "VersionHash": "oob4lno7z3G1DuB/t2qY+ih94sE="
  },
  "25,-268": {
    "SourceVersionHash": "I8aToo+SQcdBh2GHRwH3xqeuTxY=",
    "VersionHash": "oob4lno7z3G1DuB/t2qY+ih94sE="
  },
  "24,-268": {
    "SourceVersionHash": "I8aToo+SQcdBh2GHRwH3xqeuTxY=",
    "VersionHash": "SO+Cw1r4Qrj0uU/4pG4s6YM7kTo="
  },
  "27,-268": {
    "SourceVersionHash": "I8aToo+SQcdBh2GHRwH3xqeuTxY=",
    "VersionHash": "oTUq+Yi/yYxLFjq5drK7sX5HMGA="
  },
  "28,-268": {
    "SourceVersionHash": "I8aToo+SQcdBh2GHRwH3xqeuTxY=",
    "VersionHash": "Sn+gf5ZHZybRfjM3oIJiOMO6lPY="
  },
  "29,-268": {
    "SourceVersionHash": "I8aToo+SQcdBh2GHRwH3xqeuTxY=",
    "VersionHash": "Sn+gf5ZHZybRfjM3oIJiOMO6lPY="
  },
  "29,-267": {
    "SourceVersionHash": "I8aToo+SQcdBh2GHRwH3xqeuTxY=",
    "VersionHash": "pUa7vA2n4B0IPp70Zs8450Y6pOo="
  },
  "28,-267": {
    "SourceVersionHash": "I8aToo+SQcdBh2GHRwH3xqeuTxY=",
    "VersionHash": "pUa7vA2n4B0IPp70Zs8450Y6pOo="
  },
  "24,-267": {
    "SourceVersionHash": "I8aToo+SQcdBh2GHRwH3xqeuTxY=",
    "VersionHash": "pUa7vA2n4B0IPp70Zs8450Y6pOo="
  },
  "25,-267": {
    "SourceVersionHash": "I8aToo+SQcdBh2GHRwH3xqeuTxY=",
    "VersionHash": "pUa7vA2n4B0IPp70Zs8450Y6pOo="
  },
  "26,-267": {
    "SourceVersionHash": "I8aToo+SQcdBh2GHRwH3xqeuTxY=",
    "VersionHash": "pUa7vA2n4B0IPp70Zs8450Y6pOo="
  },
  "27,-267": {
    "SourceVersionHash": "I8aToo+SQcdBh2GHRwH3xqeuTxY=",
    "VersionHash": "pUa7vA2n4B0IPp70Zs8450Y6pOo="
  },
  "24,-266": {
    "SourceVersionHash": "I8aToo+SQcdBh2GHRwH3xqeuTxY=",
    "VersionHash": "pUa7vA2n4B0IPp70Zs8450Y6pOo="
  },
  "26,-266": {
    "SourceVersionHash": "I8aToo+SQcdBh2GHRwH3xqeuTxY=",
    "VersionHash": "pUa7vA2n4B0IPp70Zs8450Y6pOo="
  },
  "25,-266": {
    "SourceVersionHash": "I8aToo+SQcdBh2GHRwH3xqeuTxY=",
    "VersionHash": "pUa7vA2n4B0IPp70Zs8450Y6pOo="
  },
  "27,-266": {
    "SourceVersionHash": "I8aToo+SQcdBh2GHRwH3xqeuTxY=",
    "VersionHash": "pUa7vA2n4B0IPp70Zs8450Y6pOo="
  },
  "28,-266": {
    "SourceVersionHash": "I8aToo+SQcdBh2GHRwH3xqeuTxY=",
    "VersionHash": "pUa7vA2n4B0IPp70Zs8450Y6pOo="
  },
  "29,-266": {
    "SourceVersionHash": "I8aToo+SQcdBh2GHRwH3xqeuTxY=",
    "VersionHash": "pUa7vA2n4B0IPp70Zs8450Y6pOo="
  },
  "24,-265": {
    "SourceVersionHash": "I8aToo+SQcdBh2GHRwH3xqeuTxY=",
    "VersionHash": "7pdJdlEVhBnb4DHB0LqRaI4feuQ="
  },
  "27,-265": {
    "SourceVersionHash": "I8aToo+SQcdBh2GHRwH3xqeuTxY=",
    "VersionHash": "7pdJdlEVhBnb4DHB0LqRaI4feuQ="
  },
  "26,-265": {
    "SourceVersionHash": "I8aToo+SQcdBh2GHRwH3xqeuTxY=",
    "VersionHash": "7pdJdlEVhBnb4DHB0LqRaI4feuQ="
  },
  "25,-265": {
    "SourceVersionHash": "I8aToo+SQcdBh2GHRwH3xqeuTxY=",
    "VersionHash": "7pdJdlEVhBnb4DHB0LqRaI4feuQ="
  },
  "28,-265": {
    "SourceVersionHash": "I8aToo+SQcdBh2GHRwH3xqeuTxY=",
    "VersionHash": "7pdJdlEVhBnb4DHB0LqRaI4feuQ="
  },
  "29,-265": {
    "SourceVersionHash": "I8aToo+SQcdBh2GHRwH3xqeuTxY=",
    "VersionHash": "7pdJdlEVhBnb4DHB0LqRaI4feuQ="
  }
}