{
  "-112,-76": {
    "SourceVersionHash": "xbEpX//NF1QAd+wV9rs7hoKC4Ic=",
    "VersionHash": "fCZfGZKapEfhiZnXW+hDjnZcaVc="
  },
  "-112,-79": {
    "SourceVersionHash": "xbEpX//NF1QAd+wV9rs7hoKC4Ic=",
    "VersionHash": "fCZfGZKapEfhiZnXW+hDjnZcaVc="
  },
  "-111,-74": {
    "SourceVersionHash": "xbEpX//NF1QAd+wV9rs7hoKC4Ic=",
    "VersionHash": "fCZfGZKapEfhiZnXW+hDjnZcaVc="
  },
  "-112,-77": {
    "SourceVersionHash": "xbEpX//NF1QAd+wV9rs7hoKC4Ic=",
    "VersionHash": "fCZfGZKapEfhiZnXW+hDjnZcaVc="
  },
  "-111,-79": {
    "SourceVersionHash": "xbEpX//NF1QAd+wV9rs7hoKC4Ic=",
    "VersionHash": "fCZfGZKapEfhiZnXW+hDjnZcaVc="
  },
  "-111,-77": {
    "SourceVersionHash": "xbEpX//NF1QAd+wV9rs7hoKC4Ic=",
    "VersionHash": "fCZfGZKapEfhiZnXW+hDjnZcaVc="
  },
  "-111,-78": {
    "SourceVersionHash": "xbEpX//NF1QAd+wV9rs7hoKC4Ic=",
    "VersionHash": "fCZfGZKapEfhiZnXW+hDjnZcaVc="
  },
  "-112,-74": {
    "SourceVersionHash": "xbEpX//NF1QAd+wV9rs7hoKC4Ic=",
    "VersionHash": "fCZfGZKapEfhiZnXW+hDjnZcaVc="
  },
  "-111,-76": {
    "SourceVersionHash": "xbEpX//NF1QAd+wV9rs7hoKC4Ic=",
    "VersionHash": "fCZfGZKapEfhiZnXW+hDjnZcaVc="
  },
  "-111,-80": {
    "SourceVersionHash": "xbEpX//NF1QAd+wV9rs7hoKC4Ic=",
    "VersionHash": "fCZfGZKapEfhiZnXW+hDjnZcaVc="
  },
  "-112,-78": {
    "SourceVersionHash": "xbEpX//NF1QAd+wV9rs7hoKC4Ic=",
    "VersionHash": "fCZfGZKapEfhiZnXW+hDjnZcaVc="
  },
  "-111,-75": {
    "SourceVersionHash": "xbEpX//NF1QAd+wV9rs7hoKC4Ic=",
    "VersionHash": "fCZfGZKapEfhiZnXW+hDjnZcaVc="
  },
  "-112,-75": {
    "SourceVersionHash": "xbEpX//NF1QAd+wV9rs7hoKC4Ic=",
    "VersionHash": "fCZfGZKapEfhiZnXW+hDjnZcaVc="
  },
  "-111,-73": {
    "SourceVersionHash": "xbEpX//NF1QAd+wV9rs7hoKC4Ic=",
    "VersionHash": "fCZfGZKapEfhiZnXW+hDjnZcaVc="
  },
  "-112,-80": {
    "SourceVersionHash": "xbEpX//NF1QAd+wV9rs7hoKC4Ic=",
    "VersionHash": "fCZfGZKapEfhiZnXW+hDjnZcaVc="
  },
  "-112,-73": {
    "SourceVersionHash": "xbEpX//NF1QAd+wV9rs7hoKC4Ic=",
    "VersionHash": "fCZfGZKapEfhiZnXW+hDjnZcaVc="
  }
}