{
  "255,-96": {
    "SourceVersionHash": "xbEpX//NF1QAd+wV9rs7hoKC4Ic=",
    "VersionHash": "I2W/MIEr+Tjz67zGWXQsTfvBSGY="
  },
  "250,-96": {
    "SourceVersionHash": "xbEpX//NF1QAd+wV9rs7hoKC4Ic=",
    "VersionHash": "I2W/MIEr+Tjz67zGWXQsTfvBSGY="
  },
  "251,-96": {
    "SourceVersionHash": "xbEpX//NF1QAd+wV9rs7hoKC4Ic=",
    "VersionHash": "I2W/MIEr+Tjz67zGWXQsTfvBSGY="
  },
  "255,-95": {
    "SourceVersionHash": "xbEpX//NF1QAd+wV9rs7hoKC4Ic=",
    "VersionHash": "I2W/MIEr+Tjz67zGWXQsTfvBSGY="
  },
  "255,-93": {
    "SourceVersionHash": "xbEpX//NF1QAd+wV9rs7hoKC4Ic=",
    "VersionHash": "I2W/MIEr+Tjz67zGWXQsTfvBSGY="
  },
  "255,-94": {
    "SourceVersionHash": "xbEpX//NF1QAd+wV9rs7hoKC4Ic=",
    "VersionHash": "I2W/MIEr+Tjz67zGWXQsTfvBSGY="
  },
  "252,-96": {
    "SourceVersionHash": "xbEpX//NF1QAd+wV9rs7hoKC4Ic=",
    "VersionHash": "I2W/MIEr+Tjz67zGWXQsTfvBSGY="
  },
  "253,-96": {
    "SourceVersionHash": "xbEpX//NF1QAd+wV9rs7hoKC4Ic=",
    "VersionHash": "I2W/MIEr+Tjz67zGWXQsTfvBSGY="
  },
  "254,-96": {
    "SourceVersionHash": "xbEpX//NF1QAd+wV9rs7hoKC4Ic=",
    "VersionHash": "I2W/MIEr+Tjz67zGWXQsTfvBSGY="
  },
  "255,-91": {
    "SourceVersionHash": "xbEpX//NF1QAd+wV9rs7hoKC4Ic=",
    "VersionHash": "I2W/MIEr+Tjz67zGWXQsTfvBSGY="
  },
  "255,-92": {
    "SourceVersionHash": "xbEpX//NF1QAd+wV9rs7hoKC4Ic=",
    "VersionHash": "I2W/MIEr+Tjz67zGWXQsTfvBSGY="
  },
  "250,-95": {
    "SourceVersionHash": "xbEpX//NF1QAd+wV9rs7hoKC4Ic=",
    "VersionHash": "I2W/MIEr+Tjz67zGWXQsTfvBSGY="
  },
  "251,-95": {
    "SourceVersionHash": "xbEpX//NF1QAd+wV9rs7hoKC4Ic=",
    "VersionHash": "I2W/MIEr+Tjz67zGWXQsTfvBSGY="
  },
  "253,-95": {
    "SourceVersionHash": "xbEpX//NF1QAd+wV9rs7hoKC4Ic=",
    "VersionHash": "I2W/MIEr+Tjz67zGWXQsTfvBSGY="
  },
  "254,-95": {
    "SourceVersionHash": "xbEpX//NF1QAd+wV9rs7hoKC4Ic=",
    "VersionHash": "I2W/MIEr+Tjz67zGWXQsTfvBSGY="
  },
  "250,-94": {
    "SourceVersionHash": "xbEpX//NF1QAd+wV9rs7hoKC4Ic=",
    "VersionHash": "owVg/brQYNiOYJ585poSShzIsFs="
  },
  "251,-94": {
    "SourceVersionHash": "xbEpX//NF1QAd+wV9rs7hoKC4Ic=",
    "VersionHash": "owVg/brQYNiOYJ585poSShzIsFs="
  },
  "252,-95": {
    "SourceVersionHash": "xbEpX//NF1QAd+wV9rs7hoKC4Ic=",
    "VersionHash": "owVg/brQYNiOYJ585poSShzIsFs="
  },
  "254,-94": {
    "SourceVersionHash": "xbEpX//NF1QAd+wV9rs7hoKC4Ic=",
    "VersionHash": "owVg/brQYNiOYJ585poSShzIsFs="
  },
  "253,-94": {
    "SourceVersionHash": "xbEpX//NF1QAd+wV9rs7hoKC4Ic=",
    "VersionHash": "owVg/brQYNiOYJ585poSShzIsFs="
  },
  "250,-93": {
    "SourceVersionHash": "xbEpX//NF1QAd+wV9rs7hoKC4Ic=",
    "VersionHash": "owVg/brQYNiOYJ585poSShzIsFs="
  },
  "252,-94": {
    "SourceVersionHash": "xbEpX//NF1QAd+wV9rs7hoKC4Ic=",
    "VersionHash": "owVg/brQYNiOYJ585poSShzIsFs="
  },
  "251,-93": {
    "SourceVersionHash": "xbEpX//NF1QAd+wV9rs7hoKC4Ic=",
    "VersionHash": "owVg/brQYNiOYJ585poSShzIsFs="
  },
  "252,-93": {
    "SourceVersionHash": "xbEpX//NF1QAd+wV9rs7hoKC4Ic=",
    "VersionHash": "owVg/brQYNiOYJ585poSShzIsFs="
  },
  "253,-93": {
    "SourceVersionHash": "xbEpX//NF1QAd+wV9rs7hoKC4Ic=",
    "VersionHash": "owVg/brQYNiOYJ585poSShzIsFs="
  },
  "254,-93": {
    "SourceVersionHash": "xbEpX//NF1QAd+wV9rs7hoKC4Ic=",
    "VersionHash": "owVg/brQYNiOYJ585poSShzIsFs="
  },
  "250,-92": {
    "SourceVersionHash": "xbEpX//NF1QAd+wV9rs7hoKC4Ic=",
    "VersionHash": "owVg/brQYNiOYJ585poSShzIsFs="
  },
  "251,-92": {
    "SourceVersionHash": "xbEpX//NF1QAd+wV9rs7hoKC4Ic=",
    "VersionHash": "owVg/brQYNiOYJ585poSShzIsFs="
  },
  "252,-92": {
    "SourceVersionHash": "xbEpX//NF1QAd+wV9rs7hoKC4Ic=",
    "VersionHash": "owVg/brQYNiOYJ585poSShzIsFs="
  },
  "253,-92": {
    "SourceVersionHash": "xbEpX//NF1QAd+wV9rs7hoKC4Ic=",
    "VersionHash": "owVg/brQYNiOYJ585poSShzIsFs="
  },
  "254,-92": {
    "SourceVersionHash": "xbEpX//NF1QAd+wV9rs7hoKC4Ic=",
    "VersionHash": "owVg/brQYNiOYJ585poSShzIsFs="
  },
  "250,-91": {
    "SourceVersionHash": "xbEpX//NF1QAd+wV9rs7hoKC4Ic=",
    "VersionHash": "owVg/brQYNiOYJ585poSShzIsFs="
  },
  "251,-91": {
    "SourceVersionHash": "xbEpX//NF1QAd+wV9rs7hoKC4Ic=",
    "VersionHash": "owVg/brQYNiOYJ585poSShzIsFs="
  },
  "253,-91": {
    "SourceVersionHash": "xbEpX//NF1QAd+wV9rs7hoKC4Ic=",
    "VersionHash": "owVg/brQYNiOYJ585poSShzIsFs="
  },
  "254,-91": {
    "SourceVersionHash": "xbEpX//NF1QAd+wV9rs7hoKC4Ic=",
    "VersionHash": "owVg/brQYNiOYJ585poSShzIsFs="
  },
  "252,-91": {
    "SourceVersionHash": "xbEpX//NF1QAd+wV9rs7hoKC4Ic=",
    "VersionHash": "owVg/brQYNiOYJ585poSShzIsFs="
  }
}