{
  "-223,-136": {
    "SourceVersionHash": "xbEpX//NF1QAd+wV9rs7hoKC4Ic=",
    "VersionHash": "imU6saWLMAP2spe/0hBVUK04D10="
  },
  "-221,-135": {
    "SourceVersionHash": "xbEpX//NF1QAd+wV9rs7hoKC4Ic=",
    "VersionHash": "imU6saWLMAP2spe/0hBVUK04D10="
  },
  "-224,-136": {
    "SourceVersionHash": "xbEpX//NF1QAd+wV9rs7hoKC4Ic=",
    "VersionHash": "imU6saWLMAP2spe/0hBVUK04D10="
  },
  "-222,-135": {
    "SourceVersionHash": "xbEpX//NF1QAd+wV9rs7hoKC4Ic=",
    "VersionHash": "imU6saWLMAP2spe/0hBVUK04D10="
  },
  "-224,-135": {
    "SourceVersionHash": "xbEpX//NF1QAd+wV9rs7hoKC4Ic=",
    "VersionHash": "imU6saWLMAP2spe/0hBVUK04D10="
  },
  "-221,-136": {
    "SourceVersionHash": "xbEpX//NF1QAd+wV9rs7hoKC4Ic=",
    "VersionHash": "ZuZSXmicmzXnFSeKdJ2kgUNEO6k="
  },
  "-223,-135": {
    "SourceVersionHash": "xbEpX//NF1QAd+wV9rs7hoKC4Ic=",
    "VersionHash": "ZuZSXmicmzXnFSeKdJ2kgUNEO6k="
  },
  "-222,-136": {
    "SourceVersionHash": "xbEpX//NF1QAd+wV9rs7hoKC4Ic=",
    "VersionHash": "ZuZSXmicmzXnFSeKdJ2kgUNEO6k="
  },
  "-224,-134": {
    "SourceVersionHash": "xbEpX//NF1QAd+wV9rs7hoKC4Ic=",
    "VersionHash": "ZuZSXmicmzXnFSeKdJ2kgUNEO6k="
  },
  "-222,-134": {
    "SourceVersionHash": "xbEpX//NF1QAd+wV9rs7hoKC4Ic=",
    "VersionHash": "ZuZSXmicmzXnFSeKdJ2kgUNEO6k="
  },
  "-221,-134": {
    "SourceVersionHash": "xbEpX//NF1QAd+wV9rs7hoKC4Ic=",
    "VersionHash": "ZuZSXmicmzXnFSeKdJ2kgUNEO6k="
  },
  "-223,-133": {
    "SourceVersionHash": "xbEpX//NF1QAd+wV9rs7hoKC4Ic=",
    "VersionHash": "ZuZSXmicmzXnFSeKdJ2kgUNEO6k="
  },
  "-222,-133": {
    "SourceVersionHash": "xbEpX//NF1QAd+wV9rs7hoKC4Ic=",
    "VersionHash": "ZuZSXmicmzXnFSeKdJ2kgUNEO6k="
  },
  "-224,-133": {
    "SourceVersionHash": "xbEpX//NF1QAd+wV9rs7hoKC4Ic=",
    "VersionHash": "ZuZSXmicmzXnFSeKdJ2kgUNEO6k="
  },
  "-224,-132": {
    "SourceVersionHash": "xbEpX//NF1QAd+wV9rs7hoKC4Ic=",
    "VersionHash": "ZuZSXmicmzXnFSeKdJ2kgUNEO6k="
  },
  "-222,-132": {
    "SourceVersionHash": "xbEpX//NF1QAd+wV9rs7hoKC4Ic=",
    "VersionHash": "ZuZSXmicmzXnFSeKdJ2kgUNEO6k="
  },
  "-223,-132": {
    "SourceVersionHash": "xbEpX//NF1QAd+wV9rs7hoKC4Ic=",
    "VersionHash": "ZuZSXmicmzXnFSeKdJ2kgUNEO6k="
  },
  "-221,-133": {
    "SourceVersionHash": "xbEpX//NF1QAd+wV9rs7hoKC4Ic=",
    "VersionHash": "ZuZSXmicmzXnFSeKdJ2kgUNEO6k="
  },
  "-222,-131": {
    "SourceVersionHash": "xbEpX//NF1QAd+wV9rs7hoKC4Ic=",
    "VersionHash": "ZuZSXmicmzXnFSeKdJ2kgUNEO6k="
  },
  "-224,-131": {
    "SourceVersionHash": "xbEpX//NF1QAd+wV9rs7hoKC4Ic=",
    "VersionHash": "ZuZSXmicmzXnFSeKdJ2kgUNEO6k="
  },
  "-221,-132": {
    "SourceVersionHash": "xbEpX//NF1QAd+wV9rs7hoKC4Ic=",
    "VersionHash": "ZuZSXmicmzXnFSeKdJ2kgUNEO6k="
  },
  "-223,-134": {
    "SourceVersionHash": "xbEpX//NF1QAd+wV9rs7hoKC4Ic=",
    "VersionHash": "ZuZSXmicmzXnFSeKdJ2kgUNEO6k="
  },
  "-223,-131": {
    "SourceVersionHash": "xbEpX//NF1QAd+wV9rs7hoKC4Ic=",
    "VersionHash": "ZuZSXmicmzXnFSeKdJ2kgUNEO6k="
  },
  "-221,-131": {
    "SourceVersionHash": "xbEpX//NF1QAd+wV9rs7hoKC4Ic=",
    "VersionHash": "ZuZSXmicmzXnFSeKdJ2kgUNEO6k="
  }
}