{
  "-49,30": {
    "SourceVersionHash": "xbEpX//NF1QAd+wV9rs7hoKC4Ic=",
    "VersionHash": "3RNecqEKEF88tT/RJYUregNXJnM="
  },
  "-49,31": {
    "SourceVersionHash": "xbEpX//NF1QAd+wV9rs7hoKC4Ic=",
    "VersionHash": "3RNecqEKEF88tT/RJYUregNXJnM="
  },
  "-50,31": {
    "SourceVersionHash": "xbEpX//NF1QAd+wV9rs7hoKC4Ic=",
    "VersionHash": "3RNecqEKEF88tT/RJYUregNXJnM="
  },
  "-50,30": {
    "SourceVersionHash": "xbEpX//NF1QAd+wV9rs7hoKC4Ic=",
    "VersionHash": "3RNecqEKEF88tT/RJYUregNXJnM="
  }
}