{
  "73,69": {
    "SourceVersionHash": "xbEpX//NF1QAd+wV9rs7hoKC4Ic=",
    "VersionHash": "1X3aVKoheXJnMuW/SiSzUe/u0G8="
  },
  "74,69": {
    "SourceVersionHash": "xbEpX//NF1QAd+wV9rs7hoKC4Ic=",
    "VersionHash": "1X3aVKoheXJnMuW/SiSzUe/u0G8="
  },
  "72,69": {
    "SourceVersionHash": "xbEpX//NF1QAd+wV9rs7hoKC4Ic=",
    "VersionHash": "1X3aVKoheXJnMuW/SiSzUe/u0G8="
  },
  "72,68": {
    "SourceVersionHash": "xbEpX//NF1QAd+wV9rs7hoKC4Ic=",
    "VersionHash": "1X3aVKoheXJnMuW/SiSzUe/u0G8="
  },
  "74,68": {
    "SourceVersionHash": "xbEpX//NF1QAd+wV9rs7hoKC4Ic=",
    "VersionHash": "1X3aVKoheXJnMuW/SiSzUe/u0G8="
  },
  "73,68": {
    "SourceVersionHash": "xbEpX//NF1QAd+wV9rs7hoKC4Ic=",
    "VersionHash": "1X3aVKoheXJnMuW/SiSzUe/u0G8="
  },
  "75,69": {
    "SourceVersionHash": "xbEpX//NF1QAd+wV9rs7hoKC4Ic=",
    "VersionHash": "1X3aVKoheXJnMuW/SiSzUe/u0G8="
  },
  "75,68": {
    "SourceVersionHash": "xbEpX//NF1QAd+wV9rs7hoKC4Ic=",
    "VersionHash": "1X3aVKoheXJnMuW/SiSzUe/u0G8="
  },
  "73,60": {
    "SourceVersionHash": "CdjE2eyJERitiQV+zeTZA6R7uDM=",
    "VersionHash": "d89IDK1Muw9fwa75IX5bYh8WLAk="
  },
  "73,61": {
    "SourceVersionHash": "CdjE2eyJERitiQV+zeTZA6R7uDM=",
    "VersionHash": "d89IDK1Muw9fwa75IX5bYh8WLAk="
  },
  "72,60": {
    "SourceVersionHash": "CdjE2eyJERitiQV+zeTZA6R7uDM=",
    "VersionHash": "d89IDK1Muw9fwa75IX5bYh8WLAk="
  },
  "75,60": {
    "SourceVersionHash": "CdjE2eyJERitiQV+zeTZA6R7uDM=",
    "VersionHash": "d89IDK1Muw9fwa75IX5bYh8WLAk="
  },
  "74,61": {
    "SourceVersionHash": "CdjE2eyJERitiQV+zeTZA6R7uDM=",
    "VersionHash": "d89IDK1Muw9fwa75IX5bYh8WLAk="
  },
  "72,62": {
    "SourceVersionHash": "CdjE2eyJERitiQV+zeTZA6R7uDM=",
    "VersionHash": "d89IDK1Muw9fwa75IX5bYh8WLAk="
  },
  "75,61": {
    "SourceVersionHash": "CdjE2eyJERitiQV+zeTZA6R7uDM=",
    "VersionHash": "d89IDK1Muw9fwa75IX5bYh8WLAk="
  },
  "72,61": {
    "SourceVersionHash": "CdjE2eyJERitiQV+zeTZA6R7uDM=",
    "VersionHash": "d89IDK1Muw9fwa75IX5bYh8WLAk="
  },
  "73,63": {
    "SourceVersionHash": "CdjE2eyJERitiQV+zeTZA6R7uDM=",
    "VersionHash": "d89IDK1Muw9fwa75IX5bYh8WLAk="
  },
  "74,63": {
    "SourceVersionHash": "CdjE2eyJERitiQV+zeTZA6R7uDM=",
    "VersionHash": "d89IDK1Muw9fwa75IX5bYh8WLAk="
  },
  "75,63": {
    "SourceVersionHash": "CdjE2eyJERitiQV+zeTZA6R7uDM=",
    "VersionHash": "d89IDK1Muw9fwa75IX5bYh8WLAk="
  },
  "73,62": {
    "SourceVersionHash": "CdjE2eyJERitiQV+zeTZA6R7uDM=",
    "VersionHash": "d89IDK1Muw9fwa75IX5bYh8WLAk="
  },
  "74,60": {
    "SourceVersionHash": "CdjE2eyJERitiQV+zeTZA6R7uDM=",
    "VersionHash": "d89IDK1Muw9fwa75IX5bYh8WLAk="
  },
  "74,62": {
    "SourceVersionHash": "CdjE2eyJERitiQV+zeTZA6R7uDM=",
    "VersionHash": "d89IDK1Muw9fwa75IX5bYh8WLAk="
  },
  "75,62": {
    "SourceVersionHash": "CdjE2eyJERitiQV+zeTZA6R7uDM=",
    "VersionHash": "d89IDK1Muw9fwa75IX5bYh8WLAk="
  },
  "72,63": {
    "SourceVersionHash": "CdjE2eyJERitiQV+zeTZA6R7uDM=",
    "VersionHash": "SxeQTKlnlIRUQC/PEXb5Iawfw5Y="
  }
}