{
  "140,72": {
    "SourceVersionHash": "I8aToo+SQcdBh2GHRwH3xqeuTxY=",
    "VersionHash": "owVg/brQYNiOYJ585poSShzIsFs="
  },
  "141,72": {
    "SourceVersionHash": "I8aToo+SQcdBh2GHRwH3xqeuTxY=",
    "VersionHash": "RMHSY0uYtDc7Fpu4JGJQx0DVUOo="
  },
  "142,72": {
    "SourceVersionHash": "I8aToo+SQcdBh2GHRwH3xqeuTxY=",
    "VersionHash": "RMHSY0uYtDc7Fpu4JGJQx0DVUOo="
  },
  "143,72": {
    "SourceVersionHash": "I8aToo+SQcdBh2GHRwH3xqeuTxY=",
    "VersionHash": "RMHSY0uYtDc7Fpu4JGJQx0DVUOo="
  },
  "141,73": {
    "SourceVersionHash": "I8aToo+SQcdBh2GHRwH3xqeuTxY=",
    "VersionHash": "T4eqyKCNZmeavyvP9A58DjslVJE="
  },
  "140,73": {
    "SourceVersionHash": "I8aToo+SQcdBh2GHRwH3xqeuTxY=",
    "VersionHash": "T4eqyKCNZmeavyvP9A58DjslVJE="
  },
  "142,73": {
    "SourceVersionHash": "I8aToo+SQcdBh2GHRwH3xqeuTxY=",
    "VersionHash": "T4eqyKCNZmeavyvP9A58DjslVJE="
  },
  "143,73": {
    "SourceVersionHash": "I8aToo+SQcdBh2GHRwH3xqeuTxY=",
    "VersionHash": "T4eqyKCNZmeavyvP9A58DjslVJE="
  },
  "140,74": {
    "SourceVersionHash": "I8aToo+SQcdBh2GHRwH3xqeuTxY=",
    "VersionHash": "Zootjh8y7K0O9Rp8S7eVihBYyF0="
  },
  "141,74": {
    "SourceVersionHash": "I8aToo+SQcdBh2GHRwH3xqeuTxY=",
    "VersionHash": "Zootjh8y7K0O9Rp8S7eVihBYyF0="
  },
  "143,74": {
    "SourceVersionHash": "I8aToo+SQcdBh2GHRwH3xqeuTxY=",
    "VersionHash": "Zootjh8y7K0O9Rp8S7eVihBYyF0="
  },
  "142,74": {
    "SourceVersionHash": "I8aToo+SQcdBh2GHRwH3xqeuTxY=",
    "VersionHash": "Zootjh8y7K0O9Rp8S7eVihBYyF0="
  },
  "140,75": {
    "SourceVersionHash": "I8aToo+SQcdBh2GHRwH3xqeuTxY=",
    "VersionHash": "Zootjh8y7K0O9Rp8S7eVihBYyF0="
  },
  "141,75": {
    "SourceVersionHash": "I8aToo+SQcdBh2GHRwH3xqeuTxY=",
    "VersionHash": "L7bTCkbrvQSN6FPqdb66ArPUQt8="
  },
  "143,75": {
    "SourceVersionHash": "I8aToo+SQcdBh2GHRwH3xqeuTxY=",
    "VersionHash": "L7bTCkbrvQSN6FPqdb66ArPUQt8="
  },
  "142,75": {
    "SourceVersionHash": "I8aToo+SQcdBh2GHRwH3xqeuTxY=",
    "VersionHash": "L7bTCkbrvQSN6FPqdb66ArPUQt8="
  },
  "141,76": {
    "SourceVersionHash": "I8aToo+SQcdBh2GHRwH3xqeuTxY=",
    "VersionHash": "L7bTCkbrvQSN6FPqdb66ArPUQt8="
  },
  "142,76": {
    "SourceVersionHash": "I8aToo+SQcdBh2GHRwH3xqeuTxY=",
    "VersionHash": "L7bTCkbrvQSN6FPqdb66ArPUQt8="
  },
  "140,76": {
    "SourceVersionHash": "I8aToo+SQcdBh2GHRwH3xqeuTxY=",
    "VersionHash": "L7bTCkbrvQSN6FPqdb66ArPUQt8="
  },
  "143,76": {
    "SourceVersionHash": "I8aToo+SQcdBh2GHRwH3xqeuTxY=",
    "VersionHash": "L7bTCkbrvQSN6FPqdb66ArPUQt8="
  },
  "140,77": {
    "SourceVersionHash": "I8aToo+SQcdBh2GHRwH3xqeuTxY=",
    "VersionHash": "1D9FPAVjJGvHwflpOGHvuGnimiY="
  },
  "141,77": {
    "SourceVersionHash": "I8aToo+SQcdBh2GHRwH3xqeuTxY=",
    "VersionHash": "1D9FPAVjJGvHwflpOGHvuGnimiY="
  },
  "142,77": {
    "SourceVersionHash": "I8aToo+SQcdBh2GHRwH3xqeuTxY=",
    "VersionHash": "1D9FPAVjJGvHwflpOGHvuGnimiY="
  },
  "143,77": {
    "SourceVersionHash": "I8aToo+SQcdBh2GHRwH3xqeuTxY=",
    "VersionHash": "1D9FPAVjJGvHwflpOGHvuGnimiY="
  },
  "140,78": {
    "SourceVersionHash": "I8aToo+SQcdBh2GHRwH3xqeuTxY=",
    "VersionHash": "1D9FPAVjJGvHwflpOGHvuGnimiY="
  },
  "141,78": {
    "SourceVersionHash": "I8aToo+SQcdBh2GHRwH3xqeuTxY=",
    "VersionHash": "1D9FPAVjJGvHwflpOGHvuGnimiY="
  },
  "142,78": {
    "SourceVersionHash": "I8aToo+SQcdBh2GHRwH3xqeuTxY=",
    "VersionHash": "1D9FPAVjJGvHwflpOGHvuGnimiY="
  },
  "143,78": {
    "SourceVersionHash": "I8aToo+SQcdBh2GHRwH3xqeuTxY=",
    "VersionHash": "bI7EgtV4TsAboXTjJM/iDoCFfhI="
  },
  "140,79": {
    "SourceVersionHash": "I8aToo+SQcdBh2GHRwH3xqeuTxY=",
    "VersionHash": "bI7EgtV4TsAboXTjJM/iDoCFfhI="
  },
  "142,79": {
    "SourceVersionHash": "I8aToo+SQcdBh2GHRwH3xqeuTxY=",
    "VersionHash": "bI7EgtV4TsAboXTjJM/iDoCFfhI="
  },
  "143,79": {
    "SourceVersionHash": "I8aToo+SQcdBh2GHRwH3xqeuTxY=",
    "VersionHash": "bI7EgtV4TsAboXTjJM/iDoCFfhI="
  },
  "141,79": {
    "SourceVersionHash": "I8aToo+SQcdBh2GHRwH3xqeuTxY=",
    "VersionHash": "bI7EgtV4TsAboXTjJM/iDoCFfhI="
  }
}