{
  "121,-76": {
    "SourceVersionHash": "I8aToo+SQcdBh2GHRwH3xqeuTxY=",
    "VersionHash": "SxDZ12LQ1+vhDqVnxTooJ1+AMzo="
  },
  "123,-76": {
    "SourceVersionHash": "I8aToo+SQcdBh2GHRwH3xqeuTxY=",
    "VersionHash": "SxDZ12LQ1+vhDqVnxTooJ1+AMzo="
  },
  "123,-75": {
    "SourceVersionHash": "I8aToo+SQcdBh2GHRwH3xqeuTxY=",
    "VersionHash": "SxDZ12LQ1+vhDqVnxTooJ1+AMzo="
  },
  "120,-76": {
    "SourceVersionHash": "I8aToo+SQcdBh2GHRwH3xqeuTxY=",
    "VersionHash": "SxDZ12LQ1+vhDqVnxTooJ1+AMzo="
  },
  "121,-75": {
    "SourceVersionHash": "I8aToo+SQcdBh2GHRwH3xqeuTxY=",
    "VersionHash": "B+RKWpTOtvm0sYhy9zFVbM8SSzg="
  },
  "123,-74": {
    "SourceVersionHash": "I8aToo+SQcdBh2GHRwH3xqeuTxY=",
    "VersionHash": "B+RKWpTOtvm0sYhy9zFVbM8SSzg="
  },
  "120,-74": {
    "SourceVersionHash": "I8aToo+SQcdBh2GHRwH3xqeuTxY=",
    "VersionHash": "B+RKWpTOtvm0sYhy9zFVbM8SSzg="
  },
  "120,-75": {
    "SourceVersionHash": "I8aToo+SQcdBh2GHRwH3xqeuTxY=",
    "VersionHash": "B+RKWpTOtvm0sYhy9zFVbM8SSzg="
  },
  "122,-74": {
    "SourceVersionHash": "I8aToo+SQcdBh2GHRwH3xqeuTxY=",
    "VersionHash": "B+RKWpTOtvm0sYhy9zFVbM8SSzg="
  },
  "122,-75": {
    "SourceVersionHash": "I8aToo+SQcdBh2GHRwH3xqeuTxY=",
    "VersionHash": "B+RKWpTOtvm0sYhy9zFVbM8SSzg="
  },
  "121,-74": {
    "SourceVersionHash": "I8aToo+SQcdBh2GHRwH3xqeuTxY=",
    "VersionHash": "B+RKWpTOtvm0sYhy9zFVbM8SSzg="
  },
  "122,-76": {
    "SourceVersionHash": "I8aToo+SQcdBh2GHRwH3xqeuTxY=",
    "VersionHash": "B+RKWpTOtvm0sYhy9zFVbM8SSzg="
  },
  "123,-73": {
    "SourceVersionHash": "I8aToo+SQcdBh2GHRwH3xqeuTxY=",
    "VersionHash": "B+RKWpTOtvm0sYhy9zFVbM8SSzg="
  },
  "122,-73": {
    "SourceVersionHash": "I8aToo+SQcdBh2GHRwH3xqeuTxY=",
    "VersionHash": "B+RKWpTOtvm0sYhy9zFVbM8SSzg="
  },
  "121,-73": {
    "SourceVersionHash": "I8aToo+SQcdBh2GHRwH3xqeuTxY=",
    "VersionHash": "B+RKWpTOtvm0sYhy9zFVbM8SSzg="
  },
  "120,-73": {
    "SourceVersionHash": "I8aToo+SQcdBh2GHRwH3xqeuTxY=",
    "VersionHash": "B+RKWpTOtvm0sYhy9zFVbM8SSzg="
  }
}