{
  "23,-41": {
    "SourceVersionHash": "I8aToo+SQcdBh2GHRwH3xqeuTxY=",
    "VersionHash": "9P/bmDZpkg4orjAvGgT+Vtr/vYk="
  },
  "20,-41": {
    "SourceVersionHash": "I8aToo+SQcdBh2GHRwH3xqeuTxY=",
    "VersionHash": "9P/bmDZpkg4orjAvGgT+Vtr/vYk="
  },
  "21,-41": {
    "SourceVersionHash": "I8aToo+SQcdBh2GHRwH3xqeuTxY=",
    "VersionHash": "9P/bmDZpkg4orjAvGgT+Vtr/vYk="
  },
  "22,-41": {
    "SourceVersionHash": "I8aToo+SQcdBh2GHRwH3xqeuTxY=",
    "VersionHash": "9P/bmDZpkg4orjAvGgT+Vtr/vYk="
  },
  "23,-45": {
    "SourceVersionHash": "I8aToo+SQcdBh2GHRwH3xqeuTxY=",
    "VersionHash": "2PtGuckfIBrnuQqcaO7nG6y01GM="
  },
  "23,-42": {
    "SourceVersionHash": "I8aToo+SQcdBh2GHRwH3xqeuTxY=",
    "VersionHash": "2PtGuckfIBrnuQqcaO7nG6y01GM="
  },
  "23,-43": {
    "SourceVersionHash": "I8aToo+SQcdBh2GHRwH3xqeuTxY=",
    "VersionHash": "2PtGuckfIBrnuQqcaO7nG6y01GM="
  },
  "21,-47": {
    "SourceVersionHash": "I8aToo+SQcdBh2GHRwH3xqeuTxY=",
    "VersionHash": "2PtGuckfIBrnuQqcaO7nG6y01GM="
  },
  "23,-44": {
    "SourceVersionHash": "I8aToo+SQcdBh2GHRwH3xqeuTxY=",
    "VersionHash": "2PtGuckfIBrnuQqcaO7nG6y01GM="
  },
  "23,-47": {
    "SourceVersionHash": "I8aToo+SQcdBh2GHRwH3xqeuTxY=",
    "VersionHash": "2PtGuckfIBrnuQqcaO7nG6y01GM="
  },
  "20,-47": {
    "SourceVersionHash": "I8aToo+SQcdBh2GHRwH3xqeuTxY=",
    "VersionHash": "2PtGuckfIBrnuQqcaO7nG6y01GM="
  },
  "23,-46": {
    "SourceVersionHash": "I8aToo+SQcdBh2GHRwH3xqeuTxY=",
    "VersionHash": "2PtGuckfIBrnuQqcaO7nG6y01GM="
  },
  "22,-47": {
    "SourceVersionHash": "I8aToo+SQcdBh2GHRwH3xqeuTxY=",
    "VersionHash": "2PtGuckfIBrnuQqcaO7nG6y01GM="
  },
  "21,-48": {
    "SourceVersionHash": "I8aToo+SQcdBh2GHRwH3xqeuTxY=",
    "VersionHash": "3+LREec0hrEq+A9GnnWcAog+KNY="
  },
  "22,-48": {
    "SourceVersionHash": "I8aToo+SQcdBh2GHRwH3xqeuTxY=",
    "VersionHash": "3+LREec0hrEq+A9GnnWcAog+KNY="
  },
  "23,-48": {
    "SourceVersionHash": "I8aToo+SQcdBh2GHRwH3xqeuTxY=",
    "VersionHash": "3+LREec0hrEq+A9GnnWcAog+KNY="
  },
  "22,-46": {
    "SourceVersionHash": "I8aToo+SQcdBh2GHRwH3xqeuTxY=",
    "VersionHash": "3+LREec0hrEq+A9GnnWcAog+KNY="
  },
  "20,-48": {
    "SourceVersionHash": "I8aToo+SQcdBh2GHRwH3xqeuTxY=",
    "VersionHash": "3+LREec0hrEq+A9GnnWcAog+KNY="
  },
  "21,-46": {
    "SourceVersionHash": "I8aToo+SQcdBh2GHRwH3xqeuTxY=",
    "VersionHash": "3+LREec0hrEq+A9GnnWcAog+KNY="
  },
  "20,-46": {
    "SourceVersionHash": "I8aToo+SQcdBh2GHRwH3xqeuTxY=",
    "VersionHash": "3+LREec0hrEq+A9GnnWcAog+KNY="
  },
  "21,-45": {
    "SourceVersionHash": "I8aToo+SQcdBh2GHRwH3xqeuTxY=",
    "VersionHash": "3+LREec0hrEq+A9GnnWcAog+KNY="
  },
  "22,-45": {
    "SourceVersionHash": "I8aToo+SQcdBh2GHRwH3xqeuTxY=",
    "VersionHash": "3+LREec0hrEq+A9GnnWcAog+KNY="
  },
  "21,-44": {
    "SourceVersionHash": "I8aToo+SQcdBh2GHRwH3xqeuTxY=",
    "VersionHash": "3+LREec0hrEq+A9GnnWcAog+KNY="
  },
  "20,-45": {
    "SourceVersionHash": "I8aToo+SQcdBh2GHRwH3xqeuTxY=",
    "VersionHash": "3+LREec0hrEq+A9GnnWcAog+KNY="
  },
  "20,-44": {
    "SourceVersionHash": "I8aToo+SQcdBh2GHRwH3xqeuTxY=",
    "VersionHash": "3+LREec0hrEq+A9GnnWcAog+KNY="
  },
  "22,-44": {
    "SourceVersionHash": "I8aToo+SQcdBh2GHRwH3xqeuTxY=",
    "VersionHash": "3+LREec0hrEq+A9GnnWcAog+KNY="
  },
  "21,-43": {
    "SourceVersionHash": "I8aToo+SQcdBh2GHRwH3xqeuTxY=",
    "VersionHash": "3+LREec0hrEq+A9GnnWcAog+KNY="
  },
  "20,-43": {
    "SourceVersionHash": "I8aToo+SQcdBh2GHRwH3xqeuTxY=",
    "VersionHash": "3+LREec0hrEq+A9GnnWcAog+KNY="
  },
  "22,-43": {
    "SourceVersionHash": "I8aToo+SQcdBh2GHRwH3xqeuTxY=",
    "VersionHash": "3+LREec0hrEq+A9GnnWcAog+KNY="
  },
  "22,-42": {
    "SourceVersionHash": "I8aToo+SQcdBh2GHRwH3xqeuTxY=",
    "VersionHash": "3+LREec0hrEq+A9GnnWcAog+KNY="
  },
  "20,-42": {
    "SourceVersionHash": "I8aToo+SQcdBh2GHRwH3xqeuTxY=",
    "VersionHash": "3+LREec0hrEq+A9GnnWcAog+KNY="
  },
  "21,-42": {
    "SourceVersionHash": "I8aToo+SQcdBh2GHRwH3xqeuTxY=",
    "VersionHash": "3+LREec0hrEq+A9GnnWcAog+KNY="
  }
}