{
  "-131,109": {
    "SourceVersionHash": "CdjE2eyJERitiQV+zeTZA6R7uDM=",
    "VersionHash": "159jeizAmFH0WSSFapasYxilGYI="
  },
  "-132,109": {
    "SourceVersionHash": "CdjE2eyJERitiQV+zeTZA6R7uDM=",
    "VersionHash": "159jeizAmFH0WSSFapasYxilGYI="
  },
  "-132,108": {
    "SourceVersionHash": "CdjE2eyJERitiQV+zeTZA6R7uDM=",
    "VersionHash": "159jeizAmFH0WSSFapasYxilGYI="
  },
  "-131,108": {
    "SourceVersionHash": "CdjE2eyJERitiQV+zeTZA6R7uDM=",
    "VersionHash": "159jeizAmFH0WSSFapasYxilGYI="
  }
}