{
  "115,52": {
    "SourceVersionHash": "xbEpX//NF1QAd+wV9rs7hoKC4Ic=",
    "VersionHash": "eHfn4YaZ6kxS+ZhnizTStWlwV6A="
  },
  "112,53": {
    "SourceVersionHash": "xbEpX//NF1QAd+wV9rs7hoKC4Ic=",
    "VersionHash": "eHfn4YaZ6kxS+ZhnizTStWlwV6A="
  },
  "114,53": {
    "SourceVersionHash": "xbEpX//NF1QAd+wV9rs7hoKC4Ic=",
    "VersionHash": "eHfn4YaZ6kxS+ZhnizTStWlwV6A="
  },
  "113,53": {
    "SourceVersionHash": "xbEpX//NF1QAd+wV9rs7hoKC4Ic=",
    "VersionHash": "eHfn4YaZ6kxS+ZhnizTStWlwV6A="
  },
  "113,52": {
    "SourceVersionHash": "xbEpX//NF1QAd+wV9rs7hoKC4Ic=",
    "VersionHash": "eHfn4YaZ6kxS+ZhnizTStWlwV6A="
  },
  "115,53": {
    "SourceVersionHash": "xbEpX//NF1QAd+wV9rs7hoKC4Ic=",
    "VersionHash": "5GMEBKvGHvYSsU/2sPf1yOeWRjI="
  },
  "114,52": {
    "SourceVersionHash": "xbEpX//NF1QAd+wV9rs7hoKC4Ic=",
    "VersionHash": "5GMEBKvGHvYSsU/2sPf1yOeWRjI="
  },
  "112,52": {
    "SourceVersionHash": "xbEpX//NF1QAd+wV9rs7hoKC4Ic=",
    "VersionHash": "5GMEBKvGHvYSsU/2sPf1yOeWRjI="
  },
  "112,54": {
    "SourceVersionHash": "xbEpX//NF1QAd+wV9rs7hoKC4Ic=",
    "VersionHash": "5GMEBKvGHvYSsU/2sPf1yOeWRjI="
  },
  "112,55": {
    "SourceVersionHash": "xbEpX//NF1QAd+wV9rs7hoKC4Ic=",
    "VersionHash": "5GMEBKvGHvYSsU/2sPf1yOeWRjI="
  },
  "113,54": {
    "SourceVersionHash": "xbEpX//NF1QAd+wV9rs7hoKC4Ic=",
    "VersionHash": "5GMEBKvGHvYSsU/2sPf1yOeWRjI="
  },
  "114,54": {
    "SourceVersionHash": "xbEpX//NF1QAd+wV9rs7hoKC4Ic=",
    "VersionHash": "5GMEBKvGHvYSsU/2sPf1yOeWRjI="
  },
  "115,54": {
    "SourceVersionHash": "xbEpX//NF1QAd+wV9rs7hoKC4Ic=",
    "VersionHash": "5GMEBKvGHvYSsU/2sPf1yOeWRjI="
  },
  "113,55": {
    "SourceVersionHash": "xbEpX//NF1QAd+wV9rs7hoKC4Ic=",
    "VersionHash": "5GMEBKvGHvYSsU/2sPf1yOeWRjI="
  },
  "115,55": {
    "SourceVersionHash": "xbEpX//NF1QAd+wV9rs7hoKC4Ic=",
    "VersionHash": "5GMEBKvGHvYSsU/2sPf1yOeWRjI="
  },
  "114,55": {
    "SourceVersionHash": "xbEpX//NF1QAd+wV9rs7hoKC4Ic=",
    "VersionHash": "5GMEBKvGHvYSsU/2sPf1yOeWRjI="
  }
}