{
  "-193,-16": {
    "SourceVersionHash": "I8aToo+SQcdBh2GHRwH3xqeuTxY=",
    "VersionHash": "u7AnKV/hvJ//VeXXLjCP+1W1iRA="
  },
  "-193,-14": {
    "SourceVersionHash": "I8aToo+SQcdBh2GHRwH3xqeuTxY=",
    "VersionHash": "u7AnKV/hvJ//VeXXLjCP+1W1iRA="
  },
  "-200,-13": {
    "SourceVersionHash": "I8aToo+SQcdBh2GHRwH3xqeuTxY=",
    "VersionHash": "u7AnKV/hvJ//VeXXLjCP+1W1iRA="
  },
  "-200,-11": {
    "SourceVersionHash": "I8aToo+SQcdBh2GHRwH3xqeuTxY=",
    "VersionHash": "u7AnKV/hvJ//VeXXLjCP+1W1iRA="
  },
  "-193,-12": {
    "SourceVersionHash": "I8aToo+SQcdBh2GHRwH3xqeuTxY=",
    "VersionHash": "u7AnKV/hvJ//VeXXLjCP+1W1iRA="
  },
  "-200,-15": {
    "SourceVersionHash": "I8aToo+SQcdBh2GHRwH3xqeuTxY=",
    "VersionHash": "u7AnKV/hvJ//VeXXLjCP+1W1iRA="
  },
  "-200,-14": {
    "SourceVersionHash": "I8aToo+SQcdBh2GHRwH3xqeuTxY=",
    "VersionHash": "u7AnKV/hvJ//VeXXLjCP+1W1iRA="
  },
  "-200,-12": {
    "SourceVersionHash": "I8aToo+SQcdBh2GHRwH3xqeuTxY=",
    "VersionHash": "u7AnKV/hvJ//VeXXLjCP+1W1iRA="
  },
  "-193,-11": {
    "SourceVersionHash": "I8aToo+SQcdBh2GHRwH3xqeuTxY=",
    "VersionHash": "u7AnKV/hvJ//VeXXLjCP+1W1iRA="
  },
  "-193,-15": {
    "SourceVersionHash": "I8aToo+SQcdBh2GHRwH3xqeuTxY=",
    "VersionHash": "u7AnKV/hvJ//VeXXLjCP+1W1iRA="
  },
  "-193,-13": {
    "SourceVersionHash": "I8aToo+SQcdBh2GHRwH3xqeuTxY=",
    "VersionHash": "u7AnKV/hvJ//VeXXLjCP+1W1iRA="
  },
  "-199,-16": {
    "SourceVersionHash": "I8aToo+SQcdBh2GHRwH3xqeuTxY=",
    "VersionHash": "u7AnKV/hvJ//VeXXLjCP+1W1iRA="
  },
  "-194,-16": {
    "SourceVersionHash": "I8aToo+SQcdBh2GHRwH3xqeuTxY=",
    "VersionHash": "u7AnKV/hvJ//VeXXLjCP+1W1iRA="
  },
  "-198,-16": {
    "SourceVersionHash": "I8aToo+SQcdBh2GHRwH3xqeuTxY=",
    "VersionHash": "u7AnKV/hvJ//VeXXLjCP+1W1iRA="
  },
  "-200,-16": {
    "SourceVersionHash": "I8aToo+SQcdBh2GHRwH3xqeuTxY=",
    "VersionHash": "u7AnKV/hvJ//VeXXLjCP+1W1iRA="
  },
  "-197,-16": {
    "SourceVersionHash": "I8aToo+SQcdBh2GHRwH3xqeuTxY=",
    "VersionHash": "u7AnKV/hvJ//VeXXLjCP+1W1iRA="
  },
  "-196,-16": {
    "SourceVersionHash": "I8aToo+SQcdBh2GHRwH3xqeuTxY=",
    "VersionHash": "u7AnKV/hvJ//VeXXLjCP+1W1iRA="
  },
  "-199,-15": {
    "SourceVersionHash": "I8aToo+SQcdBh2GHRwH3xqeuTxY=",
    "VersionHash": "u7AnKV/hvJ//VeXXLjCP+1W1iRA="
  },
  "-194,-15": {
    "SourceVersionHash": "I8aToo+SQcdBh2GHRwH3xqeuTxY=",
    "VersionHash": "u7AnKV/hvJ//VeXXLjCP+1W1iRA="
  },
  "-198,-14": {
    "SourceVersionHash": "I8aToo+SQcdBh2GHRwH3xqeuTxY=",
    "VersionHash": "u7AnKV/hvJ//VeXXLjCP+1W1iRA="
  },
  "-197,-15": {
    "SourceVersionHash": "I8aToo+SQcdBh2GHRwH3xqeuTxY=",
    "VersionHash": "u7AnKV/hvJ//VeXXLjCP+1W1iRA="
  },
  "-197,-14": {
    "SourceVersionHash": "I8aToo+SQcdBh2GHRwH3xqeuTxY=",
    "VersionHash": "u7AnKV/hvJ//VeXXLjCP+1W1iRA="
  },
  "-194,-14": {
    "SourceVersionHash": "I8aToo+SQcdBh2GHRwH3xqeuTxY=",
    "VersionHash": "u7AnKV/hvJ//VeXXLjCP+1W1iRA="
  },
  "-198,-15": {
    "SourceVersionHash": "I8aToo+SQcdBh2GHRwH3xqeuTxY=",
    "VersionHash": "u7AnKV/hvJ//VeXXLjCP+1W1iRA="
  },
  "-199,-14": {
    "SourceVersionHash": "I8aToo+SQcdBh2GHRwH3xqeuTxY=",
    "VersionHash": "u7AnKV/hvJ//VeXXLjCP+1W1iRA="
  },
  "-198,-13": {
    "SourceVersionHash": "I8aToo+SQcdBh2GHRwH3xqeuTxY=",
    "VersionHash": "u7AnKV/hvJ//VeXXLjCP+1W1iRA="
  },
  "-195,-14": {
    "SourceVersionHash": "I8aToo+SQcdBh2GHRwH3xqeuTxY=",
    "VersionHash": "u7AnKV/hvJ//VeXXLjCP+1W1iRA="
  },
  "-199,-13": {
    "SourceVersionHash": "I8aToo+SQcdBh2GHRwH3xqeuTxY=",
    "VersionHash": "u7AnKV/hvJ//VeXXLjCP+1W1iRA="
  },
  "-197,-13": {
    "SourceVersionHash": "I8aToo+SQcdBh2GHRwH3xqeuTxY=",
    "VersionHash": "u7AnKV/hvJ//VeXXLjCP+1W1iRA="
  },
  "-195,-15": {
    "SourceVersionHash": "I8aToo+SQcdBh2GHRwH3xqeuTxY=",
    "VersionHash": "u7AnKV/hvJ//VeXXLjCP+1W1iRA="
  },
  "-199,-12": {
    "SourceVersionHash": "I8aToo+SQcdBh2GHRwH3xqeuTxY=",
    "VersionHash": "u7AnKV/hvJ//VeXXLjCP+1W1iRA="
  },
  "-196,-15": {
    "SourceVersionHash": "I8aToo+SQcdBh2GHRwH3xqeuTxY=",
    "VersionHash": "u7AnKV/hvJ//VeXXLjCP+1W1iRA="
  },
  "-194,-13": {
    "SourceVersionHash": "I8aToo+SQcdBh2GHRwH3xqeuTxY=",
    "VersionHash": "u7AnKV/hvJ//VeXXLjCP+1W1iRA="
  },
  "-196,-12": {
    "SourceVersionHash": "I8aToo+SQcdBh2GHRwH3xqeuTxY=",
    "VersionHash": "u7AnKV/hvJ//VeXXLjCP+1W1iRA="
  },
  "-198,-12": {
    "SourceVersionHash": "I8aToo+SQcdBh2GHRwH3xqeuTxY=",
    "VersionHash": "u7AnKV/hvJ//VeXXLjCP+1W1iRA="
  },
  "-198,-11": {
    "SourceVersionHash": "I8aToo+SQcdBh2GHRwH3xqeuTxY=",
    "VersionHash": "u7AnKV/hvJ//VeXXLjCP+1W1iRA="
  },
  "-199,-11": {
    "SourceVersionHash": "I8aToo+SQcdBh2GHRwH3xqeuTxY=",
    "VersionHash": "u7AnKV/hvJ//VeXXLjCP+1W1iRA="
  },
  "-196,-13": {
    "SourceVersionHash": "I8aToo+SQcdBh2GHRwH3xqeuTxY=",
    "VersionHash": "u7AnKV/hvJ//VeXXLjCP+1W1iRA="
  },
  "-195,-16": {
    "SourceVersionHash": "I8aToo+SQcdBh2GHRwH3xqeuTxY=",
    "VersionHash": "u7AnKV/hvJ//VeXXLjCP+1W1iRA="
  },
  "-194,-12": {
    "SourceVersionHash": "I8aToo+SQcdBh2GHRwH3xqeuTxY=",
    "VersionHash": "u7AnKV/hvJ//VeXXLjCP+1W1iRA="
  },
  "-196,-11": {
    "SourceVersionHash": "I8aToo+SQcdBh2GHRwH3xqeuTxY=",
    "VersionHash": "u7AnKV/hvJ//VeXXLjCP+1W1iRA="
  },
  "-195,-11": {
    "SourceVersionHash": "I8aToo+SQcdBh2GHRwH3xqeuTxY=",
    "VersionHash": "u7AnKV/hvJ//VeXXLjCP+1W1iRA="
  },
  "-197,-11": {
    "SourceVersionHash": "I8aToo+SQcdBh2GHRwH3xqeuTxY=",
    "VersionHash": "u7AnKV/hvJ//VeXXLjCP+1W1iRA="
  },
  "-195,-12": {
    "SourceVersionHash": "I8aToo+SQcdBh2GHRwH3xqeuTxY=",
    "VersionHash": "u7AnKV/hvJ//VeXXLjCP+1W1iRA="
  },
  "-194,-11": {
    "SourceVersionHash": "I8aToo+SQcdBh2GHRwH3xqeuTxY=",
    "VersionHash": "u7AnKV/hvJ//VeXXLjCP+1W1iRA="
  },
  "-196,-14": {
    "SourceVersionHash": "I8aToo+SQcdBh2GHRwH3xqeuTxY=",
    "VersionHash": "u7AnKV/hvJ//VeXXLjCP+1W1iRA="
  },
  "-195,-13": {
    "SourceVersionHash": "I8aToo+SQcdBh2GHRwH3xqeuTxY=",
    "VersionHash": "u7AnKV/hvJ//VeXXLjCP+1W1iRA="
  },
  "-197,-12": {
    "SourceVersionHash": "I8aToo+SQcdBh2GHRwH3xqeuTxY=",
    "VersionHash": "u7AnKV/hvJ//VeXXLjCP+1W1iRA="
  }
}