{
  "-126,-116": {
    "SourceVersionHash": "I8aToo+SQcdBh2GHRwH3xqeuTxY=",
    "VersionHash": "nU4/NJb7jO8qcn3u6lnnm+9+/60="
  },
  "-127,-116": {
    "SourceVersionHash": "I8aToo+SQcdBh2GHRwH3xqeuTxY=",
    "VersionHash": "nU4/NJb7jO8qcn3u6lnnm+9+/60="
  },
  "-127,-114": {
    "SourceVersionHash": "I8aToo+SQcdBh2GHRwH3xqeuTxY=",
    "VersionHash": "nU4/NJb7jO8qcn3u6lnnm+9+/60="
  },
  "-128,-115": {
    "SourceVersionHash": "I8aToo+SQcdBh2GHRwH3xqeuTxY=",
    "VersionHash": "nU4/NJb7jO8qcn3u6lnnm+9+/60="
  },
  "-126,-115": {
    "SourceVersionHash": "I8aToo+SQcdBh2GHRwH3xqeuTxY=",
    "VersionHash": "nU4/NJb7jO8qcn3u6lnnm+9+/60="
  },
  "-128,-116": {
    "SourceVersionHash": "I8aToo+SQcdBh2GHRwH3xqeuTxY=",
    "VersionHash": "nU4/NJb7jO8qcn3u6lnnm+9+/60="
  },
  "-126,-114": {
    "SourceVersionHash": "I8aToo+SQcdBh2GHRwH3xqeuTxY=",
    "VersionHash": "nU4/NJb7jO8qcn3u6lnnm+9+/60="
  },
  "-128,-114": {
    "SourceVersionHash": "I8aToo+SQcdBh2GHRwH3xqeuTxY=",
    "VersionHash": "nU4/NJb7jO8qcn3u6lnnm+9+/60="
  },
  "-125,-116": {
    "SourceVersionHash": "I8aToo+SQcdBh2GHRwH3xqeuTxY=",
    "VersionHash": "nU4/NJb7jO8qcn3u6lnnm+9+/60="
  },
  "-127,-113": {
    "SourceVersionHash": "I8aToo+SQcdBh2GHRwH3xqeuTxY=",
    "VersionHash": "nU4/NJb7jO8qcn3u6lnnm+9+/60="
  },
  "-127,-115": {
    "SourceVersionHash": "I8aToo+SQcdBh2GHRwH3xqeuTxY=",
    "VersionHash": "nU4/NJb7jO8qcn3u6lnnm+9+/60="
  },
  "-125,-115": {
    "SourceVersionHash": "I8aToo+SQcdBh2GHRwH3xqeuTxY=",
    "VersionHash": "nU4/NJb7jO8qcn3u6lnnm+9+/60="
  },
  "-126,-113": {
    "SourceVersionHash": "I8aToo+SQcdBh2GHRwH3xqeuTxY=",
    "VersionHash": "nU4/NJb7jO8qcn3u6lnnm+9+/60="
  },
  "-125,-114": {
    "SourceVersionHash": "I8aToo+SQcdBh2GHRwH3xqeuTxY=",
    "VersionHash": "nU4/NJb7jO8qcn3u6lnnm+9+/60="
  },
  "-125,-113": {
    "SourceVersionHash": "I8aToo+SQcdBh2GHRwH3xqeuTxY=",
    "VersionHash": "nU4/NJb7jO8qcn3u6lnnm+9+/60="
  },
  "-128,-113": {
    "SourceVersionHash": "I8aToo+SQcdBh2GHRwH3xqeuTxY=",
    "VersionHash": "nU4/NJb7jO8qcn3u6lnnm+9+/60="
  }
}