{
  "-53,-19": {
    "SourceVersionHash": "xbEpX//NF1QAd+wV9rs7hoKC4Ic=",
    "VersionHash": "U5nuUWKXPoo1vzOa7jWHoFazOps="
  },
  "-54,-19": {
    "SourceVersionHash": "xbEpX//NF1QAd+wV9rs7hoKC4Ic=",
    "VersionHash": "U5nuUWKXPoo1vzOa7jWHoFazOps="
  },
  "-54,-20": {
    "SourceVersionHash": "xbEpX//NF1QAd+wV9rs7hoKC4Ic=",
    "VersionHash": "U5nuUWKXPoo1vzOa7jWHoFazOps="
  },
  "-53,-20": {
    "SourceVersionHash": "xbEpX//NF1QAd+wV9rs7hoKC4Ic=",
    "VersionHash": "U5nuUWKXPoo1vzOa7jWHoFazOps="
  },
  "-59,-19": {
    "SourceVersionHash": "xbEpX//NF1QAd+wV9rs7hoKC4Ic=",
    "VersionHash": "H2DV3V2X4XtCvKayhT3G5TZSIb8="
  },
  "-60,-19": {
    "SourceVersionHash": "xbEpX//NF1QAd+wV9rs7hoKC4Ic=",
    "VersionHash": "H2DV3V2X4XtCvKayhT3G5TZSIb8="
  },
  "-59,-20": {
    "SourceVersionHash": "xbEpX//NF1QAd+wV9rs7hoKC4Ic=",
    "VersionHash": "H2DV3V2X4XtCvKayhT3G5TZSIb8="
  },
  "-60,-20": {
    "SourceVersionHash": "xbEpX//NF1QAd+wV9rs7hoKC4Ic=",
    "VersionHash": "H2DV3V2X4XtCvKayhT3G5TZSIb8="
  },
  "-59,-14": {
    "SourceVersionHash": "xbEpX//NF1QAd+wV9rs7hoKC4Ic=",
    "VersionHash": "H5uGDPNtYJhaTdE75ktWNYyqaoI="
  },
  "-60,-14": {
    "SourceVersionHash": "xbEpX//NF1QAd+wV9rs7hoKC4Ic=",
    "VersionHash": "H5uGDPNtYJhaTdE75ktWNYyqaoI="
  },
  "-53,-13": {
    "SourceVersionHash": "I8aToo+SQcdBh2GHRwH3xqeuTxY=",
    "VersionHash": "bTr3A2a1K8pJeA2QX/qDoIVEy20="
  },
  "-54,-14": {
    "SourceVersionHash": "I8aToo+SQcdBh2GHRwH3xqeuTxY=",
    "VersionHash": "bTr3A2a1K8pJeA2QX/qDoIVEy20="
  },
  "-53,-14": {
    "SourceVersionHash": "I8aToo+SQcdBh2GHRwH3xqeuTxY=",
    "VersionHash": "bTr3A2a1K8pJeA2QX/qDoIVEy20="
  },
  "-54,-13": {
    "SourceVersionHash": "I8aToo+SQcdBh2GHRwH3xqeuTxY=",
    "VersionHash": "bTr3A2a1K8pJeA2QX/qDoIVEy20="
  },
  "-59,-13": {
    "SourceVersionHash": "xbEpX//NF1QAd+wV9rs7hoKC4Ic=",
    "VersionHash": "bTr3A2a1K8pJeA2QX/qDoIVEy20="
  },
  "-60,-13": {
    "SourceVersionHash": "xbEpX//NF1QAd+wV9rs7hoKC4Ic=",
    "VersionHash": "bTr3A2a1K8pJeA2QX/qDoIVEy20="
  }
}