{
  "-18,1": {
    "SourceVersionHash": "yU6iyQiYeWsv06qwWyhIrstz5tY=",
    "VersionHash": "ZSTBoAdySHrwfIkGvES5Q+PPtnw="
  },
  "-18,4": {
    "SourceVersionHash": "yU6iyQiYeWsv06qwWyhIrstz5tY=",
    "VersionHash": "ZSTBoAdySHrwfIkGvES5Q+PPtnw="
  },
  "-19,1": {
    "SourceVersionHash": "yU6iyQiYeWsv06qwWyhIrstz5tY=",
    "VersionHash": "ZSTBoAdySHrwfIkGvES5Q+PPtnw="
  },
  "-18,5": {
    "SourceVersionHash": "yU6iyQiYeWsv06qwWyhIrstz5tY=",
    "VersionHash": "ZSTBoAdySHrwfIkGvES5Q+PPtnw="
  },
  "-18,2": {
    "SourceVersionHash": "yU6iyQiYeWsv06qwWyhIrstz5tY=",
    "VersionHash": "ZSTBoAdySHrwfIkGvES5Q+PPtnw="
  },
  "-18,3": {
    "SourceVersionHash": "yU6iyQiYeWsv06qwWyhIrstz5tY=",
    "VersionHash": "ZSTBoAdySHrwfIkGvES5Q+PPtnw="
  },
  "-20,1": {
    "SourceVersionHash": "yU6iyQiYeWsv06qwWyhIrstz5tY=",
    "VersionHash": "ZSTBoAdySHrwfIkGvES5Q+PPtnw="
  },
  "-18,6": {
    "SourceVersionHash": "yU6iyQiYeWsv06qwWyhIrstz5tY=",
    "VersionHash": "ZSTBoAdySHrwfIkGvES5Q+PPtnw="
  },
  "-20,5": {
    "SourceVersionHash": "yU6iyQiYeWsv06qwWyhIrstz5tY=",
    "VersionHash": "ZSTBoAdySHrwfIkGvES5Q+PPtnw="
  },
  "-20,3": {
    "SourceVersionHash": "yU6iyQiYeWsv06qwWyhIrstz5tY=",
    "VersionHash": "ZSTBoAdySHrwfIkGvES5Q+PPtnw="
  },
  "-19,2": {
    "SourceVersionHash": "yU6iyQiYeWsv06qwWyhIrstz5tY=",
    "VersionHash": "ZSTBoAdySHrwfIkGvES5Q+PPtnw="
  },
  "-20,2": {
    "SourceVersionHash": "yU6iyQiYeWsv06qwWyhIrstz5tY=",
    "VersionHash": "ZSTBoAdySHrwfIkGvES5Q+PPtnw="
  },
  "-19,3": {
    "SourceVersionHash": "yU6iyQiYeWsv06qwWyhIrstz5tY=",
    "VersionHash": "ZSTBoAdySHrwfIkGvES5Q+PPtnw="
  },
  "-20,6": {
    "SourceVersionHash": "yU6iyQiYeWsv06qwWyhIrstz5tY=",
    "VersionHash": "ZSTBoAdySHrwfIkGvES5Q+PPtnw="
  },
  "-20,4": {
    "SourceVersionHash": "yU6iyQiYeWsv06qwWyhIrstz5tY=",
    "VersionHash": "ZSTBoAdySHrwfIkGvES5Q+PPtnw="
  },
  "-19,5": {
    "SourceVersionHash": "yU6iyQiYeWsv06qwWyhIrstz5tY=",
    "VersionHash": "ZSTBoAdySHrwfIkGvES5Q+PPtnw="
  },
  "-19,6": {
    "SourceVersionHash": "yU6iyQiYeWsv06qwWyhIrstz5tY=",
    "VersionHash": "ZSTBoAdySHrwfIkGvES5Q+PPtnw="
  },
  "-19,7": {
    "SourceVersionHash": "yU6iyQiYeWsv06qwWyhIrstz5tY=",
    "VersionHash": "UfZhkh8u5vYK/cyv68Ezz5UMWu8="
  },
  "-20,7": {
    "SourceVersionHash": "yU6iyQiYeWsv06qwWyhIrstz5tY=",
    "VersionHash": "UfZhkh8u5vYK/cyv68Ezz5UMWu8="
  },
  "-18,7": {
    "SourceVersionHash": "yU6iyQiYeWsv06qwWyhIrstz5tY=",
    "VersionHash": "UfZhkh8u5vYK/cyv68Ezz5UMWu8="
  },
  "-18,8": {
    "SourceVersionHash": "9GZss1MxbbdT9ctuP9HBc+Te72w=",
    "VersionHash": "UfZhkh8u5vYK/cyv68Ezz5UMWu8="
  },
  "-19,8": {
    "SourceVersionHash": "9GZss1MxbbdT9ctuP9HBc+Te72w=",
    "VersionHash": "UfZhkh8u5vYK/cyv68Ezz5UMWu8="
  },
  "-20,8": {
    "SourceVersionHash": "9GZss1MxbbdT9ctuP9HBc+Te72w=",
    "VersionHash": "UfZhkh8u5vYK/cyv68Ezz5UMWu8="
  },
  "-19,4": {
    "SourceVersionHash": "yU6iyQiYeWsv06qwWyhIrstz5tY=",
    "VersionHash": "ZSTBoAdySHrwfIkGvES5Q+PPtnw="
  },
  "-20,0": {
    "SourceVersionHash": "yU6iyQiYeWsv06qwWyhIrstz5tY=",
    "VersionHash": "jfDYTVuWu+BBRz3SocyyIWM7ez8="
  },
  "-18,0": {
    "SourceVersionHash": "yU6iyQiYeWsv06qwWyhIrstz5tY=",
    "VersionHash": "jfDYTVuWu+BBRz3SocyyIWM7ez8="
  },
  "-19,0": {
    "SourceVersionHash": "yU6iyQiYeWsv06qwWyhIrstz5tY=",
    "VersionHash": "jfDYTVuWu+BBRz3SocyyIWM7ez8="
  },
  "-17,0": {
    "SourceVersionHash": "yU6iyQiYeWsv06qwWyhIrstz5tY=",
    "VersionHash": "3rvkMEIzqQsB0xAvGSmV6rlBx2w="
  },
  "-16,0": {
    "SourceVersionHash": "2hGSF+47938eftNvSEbz1zUktzo=",
    "VersionHash": "3rvkMEIzqQsB0xAvGSmV6rlBx2w="
  },
  "-15,0": {
    "SourceVersionHash": "2hGSF+47938eftNvSEbz1zUktzo=",
    "VersionHash": "XGxzyj21+Gj5zxpu0M522jn8BzQ="
  },
  "-13,0": {
    "SourceVersionHash": "2hGSF+47938eftNvSEbz1zUktzo=",
    "VersionHash": "XGxzyj21+Gj5zxpu0M522jn8BzQ="
  },
  "-12,0": {
    "SourceVersionHash": "2hGSF+47938eftNvSEbz1zUktzo=",
    "VersionHash": "XGxzyj21+Gj5zxpu0M522jn8BzQ="
  },
  "-14,0": {
    "SourceVersionHash": "2hGSF+47938eftNvSEbz1zUktzo=",
    "VersionHash": "XGxzyj21+Gj5zxpu0M522jn8BzQ="
  },
  "-17,1": {
    "SourceVersionHash": "yU6iyQiYeWsv06qwWyhIrstz5tY=",
    "VersionHash": "XGxzyj21+Gj5zxpu0M522jn8BzQ="
  },
  "-16,1": {
    "SourceVersionHash": "2hGSF+47938eftNvSEbz1zUktzo=",
    "VersionHash": "XGxzyj21+Gj5zxpu0M522jn8BzQ="
  },
  "-11,0": {
    "SourceVersionHash": "2hGSF+47938eftNvSEbz1zUktzo=",
    "VersionHash": "XGxzyj21+Gj5zxpu0M522jn8BzQ="
  },
  "-17,2": {
    "SourceVersionHash": "yU6iyQiYeWsv06qwWyhIrstz5tY=",
    "VersionHash": "XGxzyj21+Gj5zxpu0M522jn8BzQ="
  },
  "-16,2": {
    "SourceVersionHash": "2hGSF+47938eftNvSEbz1zUktzo=",
    "VersionHash": "XGxzyj21+Gj5zxpu0M522jn8BzQ="
  },
  "-16,3": {
    "SourceVersionHash": "2hGSF+47938eftNvSEbz1zUktzo=",
    "VersionHash": "XGxzyj21+Gj5zxpu0M522jn8BzQ="
  },
  "-17,4": {
    "SourceVersionHash": "yU6iyQiYeWsv06qwWyhIrstz5tY=",
    "VersionHash": "XGxzyj21+Gj5zxpu0M522jn8BzQ="
  },
  "-16,4": {
    "SourceVersionHash": "2hGSF+47938eftNvSEbz1zUktzo=",
    "VersionHash": "XGxzyj21+Gj5zxpu0M522jn8BzQ="
  },
  "-17,3": {
    "SourceVersionHash": "yU6iyQiYeWsv06qwWyhIrstz5tY=",
    "VersionHash": "XGxzyj21+Gj5zxpu0M522jn8BzQ="
  },
  "-17,5": {
    "SourceVersionHash": "yU6iyQiYeWsv06qwWyhIrstz5tY=",
    "VersionHash": "XGxzyj21+Gj5zxpu0M522jn8BzQ="
  },
  "-16,5": {
    "SourceVersionHash": "2hGSF+47938eftNvSEbz1zUktzo=",
    "VersionHash": "XGxzyj21+Gj5zxpu0M522jn8BzQ="
  },
  "-16,6": {
    "SourceVersionHash": "2hGSF+47938eftNvSEbz1zUktzo=",
    "VersionHash": "XGxzyj21+Gj5zxpu0M522jn8BzQ="
  },
  "-17,6": {
    "SourceVersionHash": "yU6iyQiYeWsv06qwWyhIrstz5tY=",
    "VersionHash": "XGxzyj21+Gj5zxpu0M522jn8BzQ="
  },
  "-20,9": {
    "SourceVersionHash": "9GZss1MxbbdT9ctuP9HBc+Te72w=",
    "VersionHash": "Y5HHXk7Jw4QOFweR0KEEFKrYfnk="
  },
  "-18,9": {
    "SourceVersionHash": "9GZss1MxbbdT9ctuP9HBc+Te72w=",
    "VersionHash": "Y5HHXk7Jw4QOFweR0KEEFKrYfnk="
  },
  "-19,9": {
    "SourceVersionHash": "9GZss1MxbbdT9ctuP9HBc+Te72w=",
    "VersionHash": "Y5HHXk7Jw4QOFweR0KEEFKrYfnk="
  },
  "-17,7": {
    "SourceVersionHash": "yU6iyQiYeWsv06qwWyhIrstz5tY=",
    "VersionHash": "Y5HHXk7Jw4QOFweR0KEEFKrYfnk="
  },
  "-16,7": {
    "SourceVersionHash": "2hGSF+47938eftNvSEbz1zUktzo=",
    "VersionHash": "Y5HHXk7Jw4QOFweR0KEEFKrYfnk="
  },
  "-16,8": {
    "SourceVersionHash": "fHdiM05PXoUfQl20pLLJUVRLdl0=",
    "VersionHash": "Y5HHXk7Jw4QOFweR0KEEFKrYfnk="
  },
  "-17,9": {
    "SourceVersionHash": "9GZss1MxbbdT9ctuP9HBc+Te72w=",
    "VersionHash": "Y5HHXk7Jw4QOFweR0KEEFKrYfnk="
  },
  "-16,9": {
    "SourceVersionHash": "fHdiM05PXoUfQl20pLLJUVRLdl0=",
    "VersionHash": "Va799rDwocJm6K75gDza8j952L4="
  },
  "-17,8": {
    "SourceVersionHash": "9GZss1MxbbdT9ctuP9HBc+Te72w=",
    "VersionHash": "Va799rDwocJm6K75gDza8j952L4="
  },
  "-15,9": {
    "SourceVersionHash": "fHdiM05PXoUfQl20pLLJUVRLdl0=",
    "VersionHash": "er1fJATt1tIK/UIBtGl3UXBq/Jc="
  },
  "-14,7": {
    "SourceVersionHash": "2hGSF+47938eftNvSEbz1zUktzo=",
    "VersionHash": "er1fJATt1tIK/UIBtGl3UXBq/Jc="
  },
  "-15,7": {
    "SourceVersionHash": "2hGSF+47938eftNvSEbz1zUktzo=",
    "VersionHash": "er1fJATt1tIK/UIBtGl3UXBq/Jc="
  },
  "-14,9": {
    "SourceVersionHash": "fHdiM05PXoUfQl20pLLJUVRLdl0=",
    "VersionHash": "er1fJATt1tIK/UIBtGl3UXBq/Jc="
  },
  "-13,7": {
    "SourceVersionHash": "2hGSF+47938eftNvSEbz1zUktzo=",
    "VersionHash": "er1fJATt1tIK/UIBtGl3UXBq/Jc="
  },
  "-12,7": {
    "SourceVersionHash": "2hGSF+47938eftNvSEbz1zUktzo=",
    "VersionHash": "er1fJATt1tIK/UIBtGl3UXBq/Jc="
  },
  "-11,7": {
    "SourceVersionHash": "2hGSF+47938eftNvSEbz1zUktzo=",
    "VersionHash": "er1fJATt1tIK/UIBtGl3UXBq/Jc="
  },
  "-15,8": {
    "SourceVersionHash": "fHdiM05PXoUfQl20pLLJUVRLdl0=",
    "VersionHash": "er1fJATt1tIK/UIBtGl3UXBq/Jc="
  },
  "-14,8": {
    "SourceVersionHash": "fHdiM05PXoUfQl20pLLJUVRLdl0=",
    "VersionHash": "er1fJATt1tIK/UIBtGl3UXBq/Jc="
  },
  "-13,8": {
    "SourceVersionHash": "fHdiM05PXoUfQl20pLLJUVRLdl0=",
    "VersionHash": "er1fJATt1tIK/UIBtGl3UXBq/Jc="
  },
  "-11,8": {
    "SourceVersionHash": "fHdiM05PXoUfQl20pLLJUVRLdl0=",
    "VersionHash": "er1fJATt1tIK/UIBtGl3UXBq/Jc="
  },
  "-12,8": {
    "SourceVersionHash": "fHdiM05PXoUfQl20pLLJUVRLdl0=",
    "VersionHash": "er1fJATt1tIK/UIBtGl3UXBq/Jc="
  },
  "-13,9": {
    "SourceVersionHash": "fHdiM05PXoUfQl20pLLJUVRLdl0=",
    "VersionHash": "TM1a5Zx3wc2gnRof6svCHTBoaQE="
  },
  "-12,9": {
    "SourceVersionHash": "fHdiM05PXoUfQl20pLLJUVRLdl0=",
    "VersionHash": "TM1a5Zx3wc2gnRof6svCHTBoaQE="
  },
  "-11,9": {
    "SourceVersionHash": "fHdiM05PXoUfQl20pLLJUVRLdl0=",
    "VersionHash": "TM1a5Zx3wc2gnRof6svCHTBoaQE="
  },
  "-15,1": {
    "SourceVersionHash": "2hGSF+47938eftNvSEbz1zUktzo=",
    "VersionHash": "oob4lno7z3G1DuB/t2qY+ih94sE="
  },
  "-12,1": {
    "SourceVersionHash": "2hGSF+47938eftNvSEbz1zUktzo=",
    "VersionHash": "oob4lno7z3G1DuB/t2qY+ih94sE="
  },
  "-14,1": {
    "SourceVersionHash": "2hGSF+47938eftNvSEbz1zUktzo=",
    "VersionHash": "oob4lno7z3G1DuB/t2qY+ih94sE="
  },
  "-13,1": {
    "SourceVersionHash": "2hGSF+47938eftNvSEbz1zUktzo=",
    "VersionHash": "oob4lno7z3G1DuB/t2qY+ih94sE="
  },
  "-11,1": {
    "SourceVersionHash": "2hGSF+47938eftNvSEbz1zUktzo=",
    "VersionHash": "SO+Cw1r4Qrj0uU/4pG4s6YM7kTo="
  },
  "-15,2": {
    "SourceVersionHash": "2hGSF+47938eftNvSEbz1zUktzo=",
    "VersionHash": "pNvGtwI3+2IQGYSrtA/6A6jNEQY="
  },
  "-14,2": {
    "SourceVersionHash": "2hGSF+47938eftNvSEbz1zUktzo=",
    "VersionHash": "oTUq+Yi/yYxLFjq5drK7sX5HMGA="
  },
  "-12,2": {
    "SourceVersionHash": "2hGSF+47938eftNvSEbz1zUktzo=",
    "VersionHash": "Sn+gf5ZHZybRfjM3oIJiOMO6lPY="
  },
  "-11,2": {
    "SourceVersionHash": "2hGSF+47938eftNvSEbz1zUktzo=",
    "VersionHash": "Sn+gf5ZHZybRfjM3oIJiOMO6lPY="
  },
  "-15,3": {
    "SourceVersionHash": "2hGSF+47938eftNvSEbz1zUktzo=",
    "VersionHash": "Sn+gf5ZHZybRfjM3oIJiOMO6lPY="
  },
  "-13,3": {
    "SourceVersionHash": "2hGSF+47938eftNvSEbz1zUktzo=",
    "VersionHash": "Sn+gf5ZHZybRfjM3oIJiOMO6lPY="
  },
  "-13,2": {
    "SourceVersionHash": "2hGSF+47938eftNvSEbz1zUktzo=",
    "VersionHash": "Sn+gf5ZHZybRfjM3oIJiOMO6lPY="
  },
  "-14,3": {
    "SourceVersionHash": "2hGSF+47938eftNvSEbz1zUktzo=",
    "VersionHash": "Sn+gf5ZHZybRfjM3oIJiOMO6lPY="
  },
  "-12,3": {
    "SourceVersionHash": "2hGSF+47938eftNvSEbz1zUktzo=",
    "VersionHash": "Sn+gf5ZHZybRfjM3oIJiOMO6lPY="
  },
  "-11,3": {
    "SourceVersionHash": "2hGSF+47938eftNvSEbz1zUktzo=",
    "VersionHash": "Sn+gf5ZHZybRfjM3oIJiOMO6lPY="
  },
  "-15,4": {
    "SourceVersionHash": "2hGSF+47938eftNvSEbz1zUktzo=",
    "VersionHash": "pUa7vA2n4B0IPp70Zs8450Y6pOo="
  },
  "-14,4": {
    "SourceVersionHash": "2hGSF+47938eftNvSEbz1zUktzo=",
    "VersionHash": "pUa7vA2n4B0IPp70Zs8450Y6pOo="
  },
  "-13,4": {
    "SourceVersionHash": "2hGSF+47938eftNvSEbz1zUktzo=",
    "VersionHash": "pUa7vA2n4B0IPp70Zs8450Y6pOo="
  },
  "-11,4": {
    "SourceVersionHash": "2hGSF+47938eftNvSEbz1zUktzo=",
    "VersionHash": "pUa7vA2n4B0IPp70Zs8450Y6pOo="
  },
  "-15,5": {
    "SourceVersionHash": "2hGSF+47938eftNvSEbz1zUktzo=",
    "VersionHash": "pUa7vA2n4B0IPp70Zs8450Y6pOo="
  },
  "-14,5": {
    "SourceVersionHash": "2hGSF+47938eftNvSEbz1zUktzo=",
    "VersionHash": "pUa7vA2n4B0IPp70Zs8450Y6pOo="
  },
  "-12,4": {
    "SourceVersionHash": "2hGSF+47938eftNvSEbz1zUktzo=",
    "VersionHash": "pUa7vA2n4B0IPp70Zs8450Y6pOo="
  },
  "-11,5": {
    "SourceVersionHash": "2hGSF+47938eftNvSEbz1zUktzo=",
    "VersionHash": "pUa7vA2n4B0IPp70Zs8450Y6pOo="
  },
  "-13,5": {
    "SourceVersionHash": "2hGSF+47938eftNvSEbz1zUktzo=",
    "VersionHash": "pUa7vA2n4B0IPp70Zs8450Y6pOo="
  },
  "-12,5": {
    "SourceVersionHash": "2hGSF+47938eftNvSEbz1zUktzo=",
    "VersionHash": "pUa7vA2n4B0IPp70Zs8450Y6pOo="
  },
  "-14,6": {
    "SourceVersionHash": "2hGSF+47938eftNvSEbz1zUktzo=",
    "VersionHash": "pUa7vA2n4B0IPp70Zs8450Y6pOo="
  },
  "-15,6": {
    "SourceVersionHash": "2hGSF+47938eftNvSEbz1zUktzo=",
    "VersionHash": "pUa7vA2n4B0IPp70Zs8450Y6pOo="
  },
  "-13,6": {
    "SourceVersionHash": "2hGSF+47938eftNvSEbz1zUktzo=",
    "VersionHash": "pUa7vA2n4B0IPp70Zs8450Y6pOo="
  },
  "-11,6": {
    "SourceVersionHash": "2hGSF+47938eftNvSEbz1zUktzo=",
    "VersionHash": "7pdJdlEVhBnb4DHB0LqRaI4feuQ="
  },
  "-12,6": {
    "SourceVersionHash": "2hGSF+47938eftNvSEbz1zUktzo=",
    "VersionHash": "7pdJdlEVhBnb4DHB0LqRaI4feuQ="
  }
}