{
  "42,7": {
    "SourceVersionHash": "xbEpX//NF1QAd+wV9rs7hoKC4Ic=",
    "VersionHash": "R8P0jdIwnaYEkE2KsPoohr1sCgA="
  },
  "42,6": {
    "SourceVersionHash": "xbEpX//NF1QAd+wV9rs7hoKC4Ic=",
    "VersionHash": "R8P0jdIwnaYEkE2KsPoohr1sCgA="
  },
  "43,7": {
    "SourceVersionHash": "xbEpX//NF1QAd+wV9rs7hoKC4Ic=",
    "VersionHash": "R8P0jdIwnaYEkE2KsPoohr1sCgA="
  },
  "43,6": {
    "SourceVersionHash": "xbEpX//NF1QAd+wV9rs7hoKC4Ic=",
    "VersionHash": "R8P0jdIwnaYEkE2KsPoohr1sCgA="
  },
  "47,2": {
    "SourceVersionHash": "I8aToo+SQcdBh2GHRwH3xqeuTxY=",
    "VersionHash": "U5nuUWKXPoo1vzOa7jWHoFazOps="
  },
  "47,3": {
    "SourceVersionHash": "I8aToo+SQcdBh2GHRwH3xqeuTxY=",
    "VersionHash": "U5nuUWKXPoo1vzOa7jWHoFazOps="
  },
  "46,3": {
    "SourceVersionHash": "I8aToo+SQcdBh2GHRwH3xqeuTxY=",
    "VersionHash": "U5nuUWKXPoo1vzOa7jWHoFazOps="
  },
  "46,2": {
    "SourceVersionHash": "I8aToo+SQcdBh2GHRwH3xqeuTxY=",
    "VersionHash": "U5nuUWKXPoo1vzOa7jWHoFazOps="
  },
  "46,6": {
    "SourceVersionHash": "xbEpX//NF1QAd+wV9rs7hoKC4Ic=",
    "VersionHash": "XkhRifkqtPmh5ByO5P3pwhR18D0="
  },
  "47,6": {
    "SourceVersionHash": "xbEpX//NF1QAd+wV9rs7hoKC4Ic=",
    "VersionHash": "XkhRifkqtPmh5ByO5P3pwhR18D0="
  },
  "46,7": {
    "SourceVersionHash": "xbEpX//NF1QAd+wV9rs7hoKC4Ic=",
    "VersionHash": "XkhRifkqtPmh5ByO5P3pwhR18D0="
  },
  "47,7": {
    "SourceVersionHash": "xbEpX//NF1QAd+wV9rs7hoKC4Ic=",
    "VersionHash": "XkhRifkqtPmh5ByO5P3pwhR18D0="
  },
  "41,0": {
    "SourceVersionHash": "I8aToo+SQcdBh2GHRwH3xqeuTxY=",
    "VersionHash": "bTr3A2a1K8pJeA2QX/qDoIVEy20="
  },
  "40,0": {
    "SourceVersionHash": "I8aToo+SQcdBh2GHRwH3xqeuTxY=",
    "VersionHash": "bTr3A2a1K8pJeA2QX/qDoIVEy20="
  },
  "41,1": {
    "SourceVersionHash": "I8aToo+SQcdBh2GHRwH3xqeuTxY=",
    "VersionHash": "bTr3A2a1K8pJeA2QX/qDoIVEy20="
  },
  "40,1": {
    "SourceVersionHash": "I8aToo+SQcdBh2GHRwH3xqeuTxY=",
    "VersionHash": "bTr3A2a1K8pJeA2QX/qDoIVEy20="
  }
}