{
  "168,81": {
    "SourceVersionHash": "I8aToo+SQcdBh2GHRwH3xqeuTxY=",
    "VersionHash": "fH+opBZY/4HGpQVQTv60AGV10ng="
  },
  "169,81": {
    "SourceVersionHash": "I8aToo+SQcdBh2GHRwH3xqeuTxY=",
    "VersionHash": "fH+opBZY/4HGpQVQTv60AGV10ng="
  },
  "168,80": {
    "SourceVersionHash": "I8aToo+SQcdBh2GHRwH3xqeuTxY=",
    "VersionHash": "fH+opBZY/4HGpQVQTv60AGV10ng="
  },
  "169,80": {
    "SourceVersionHash": "I8aToo+SQcdBh2GHRwH3xqeuTxY=",
    "VersionHash": "fH+opBZY/4HGpQVQTv60AGV10ng="
  },
  "168,82": {
    "SourceVersionHash": "I8aToo+SQcdBh2GHRwH3xqeuTxY=",
    "VersionHash": "fH+opBZY/4HGpQVQTv60AGV10ng="
  },
  "169,82": {
    "SourceVersionHash": "I8aToo+SQcdBh2GHRwH3xqeuTxY=",
    "VersionHash": "fH+opBZY/4HGpQVQTv60AGV10ng="
  },
  "168,83": {
    "SourceVersionHash": "I8aToo+SQcdBh2GHRwH3xqeuTxY=",
    "VersionHash": "fH+opBZY/4HGpQVQTv60AGV10ng="
  },
  "169,83": {
    "SourceVersionHash": "I8aToo+SQcdBh2GHRwH3xqeuTxY=",
    "VersionHash": "fH+opBZY/4HGpQVQTv60AGV10ng="
  },
  "168,84": {
    "SourceVersionHash": "I8aToo+SQcdBh2GHRwH3xqeuTxY=",
    "VersionHash": "UYWE1rmF9h4Bv17xcilMYvTSbZg="
  },
  "169,87": {
    "SourceVersionHash": "I8aToo+SQcdBh2GHRwH3xqeuTxY=",
    "VersionHash": "UYWE1rmF9h4Bv17xcilMYvTSbZg="
  },
  "169,84": {
    "SourceVersionHash": "I8aToo+SQcdBh2GHRwH3xqeuTxY=",
    "VersionHash": "UYWE1rmF9h4Bv17xcilMYvTSbZg="
  },
  "168,85": {
    "SourceVersionHash": "I8aToo+SQcdBh2GHRwH3xqeuTxY=",
    "VersionHash": "UYWE1rmF9h4Bv17xcilMYvTSbZg="
  },
  "169,85": {
    "SourceVersionHash": "I8aToo+SQcdBh2GHRwH3xqeuTxY=",
    "VersionHash": "UYWE1rmF9h4Bv17xcilMYvTSbZg="
  },
  "169,86": {
    "SourceVersionHash": "I8aToo+SQcdBh2GHRwH3xqeuTxY=",
    "VersionHash": "UYWE1rmF9h4Bv17xcilMYvTSbZg="
  },
  "168,87": {
    "SourceVersionHash": "I8aToo+SQcdBh2GHRwH3xqeuTxY=",
    "VersionHash": "UYWE1rmF9h4Bv17xcilMYvTSbZg="
  },
  "168,86": {
    "SourceVersionHash": "I8aToo+SQcdBh2GHRwH3xqeuTxY=",
    "VersionHash": "UYWE1rmF9h4Bv17xcilMYvTSbZg="
  }
}