{
  "93,151": {
    "SourceVersionHash": "CdjE2eyJERitiQV+zeTZA6R7uDM=",
    "VersionHash": "NvWZEskLYDOcf0t+KlTz/2mJJ9Y="
  },
  "91,151": {
    "SourceVersionHash": "CdjE2eyJERitiQV+zeTZA6R7uDM=",
    "VersionHash": "NvWZEskLYDOcf0t+KlTz/2mJJ9Y="
  },
  "94,151": {
    "SourceVersionHash": "CdjE2eyJERitiQV+zeTZA6R7uDM=",
    "VersionHash": "NvWZEskLYDOcf0t+KlTz/2mJJ9Y="
  },
  "90,151": {
    "SourceVersionHash": "CdjE2eyJERitiQV+zeTZA6R7uDM=",
    "VersionHash": "NvWZEskLYDOcf0t+KlTz/2mJJ9Y="
  },
  "91,150": {
    "SourceVersionHash": "CdjE2eyJERitiQV+zeTZA6R7uDM=",
    "VersionHash": "NvWZEskLYDOcf0t+KlTz/2mJJ9Y="
  },
  "92,150": {
    "SourceVersionHash": "CdjE2eyJERitiQV+zeTZA6R7uDM=",
    "VersionHash": "NvWZEskLYDOcf0t+KlTz/2mJJ9Y="
  },
  "94,150": {
    "SourceVersionHash": "CdjE2eyJERitiQV+zeTZA6R7uDM=",
    "VersionHash": "NvWZEskLYDOcf0t+KlTz/2mJJ9Y="
  },
  "93,150": {
    "SourceVersionHash": "CdjE2eyJERitiQV+zeTZA6R7uDM=",
    "VersionHash": "NvWZEskLYDOcf0t+KlTz/2mJJ9Y="
  },
  "90,150": {
    "SourceVersionHash": "CdjE2eyJERitiQV+zeTZA6R7uDM=",
    "VersionHash": "NvWZEskLYDOcf0t+KlTz/2mJJ9Y="
  },
  "95,151": {
    "SourceVersionHash": "CdjE2eyJERitiQV+zeTZA6R7uDM=",
    "VersionHash": "NvWZEskLYDOcf0t+KlTz/2mJJ9Y="
  },
  "95,150": {
    "SourceVersionHash": "CdjE2eyJERitiQV+zeTZA6R7uDM=",
    "VersionHash": "NvWZEskLYDOcf0t+KlTz/2mJJ9Y="
  },
  "92,151": {
    "SourceVersionHash": "CdjE2eyJERitiQV+zeTZA6R7uDM=",
    "VersionHash": "NvWZEskLYDOcf0t+KlTz/2mJJ9Y="
  }
}