{
  "110,-102": {
    "SourceVersionHash": "xbEpX//NF1QAd+wV9rs7hoKC4Ic=",
    "VersionHash": "fCZfGZKapEfhiZnXW+hDjnZcaVc="
  },
  "111,-102": {
    "SourceVersionHash": "xbEpX//NF1QAd+wV9rs7hoKC4Ic=",
    "VersionHash": "fCZfGZKapEfhiZnXW+hDjnZcaVc="
  },
  "110,-103": {
    "SourceVersionHash": "xbEpX//NF1QAd+wV9rs7hoKC4Ic=",
    "VersionHash": "fCZfGZKapEfhiZnXW+hDjnZcaVc="
  },
  "111,-103": {
    "SourceVersionHash": "xbEpX//NF1QAd+wV9rs7hoKC4Ic=",
    "VersionHash": "fCZfGZKapEfhiZnXW+hDjnZcaVc="
  },
  "111,-101": {
    "SourceVersionHash": "xbEpX//NF1QAd+wV9rs7hoKC4Ic=",
    "VersionHash": "fCZfGZKapEfhiZnXW+hDjnZcaVc="
  },
  "110,-101": {
    "SourceVersionHash": "xbEpX//NF1QAd+wV9rs7hoKC4Ic=",
    "VersionHash": "fCZfGZKapEfhiZnXW+hDjnZcaVc="
  },
  "111,-104": {
    "SourceVersionHash": "xbEpX//NF1QAd+wV9rs7hoKC4Ic=",
    "VersionHash": "fCZfGZKapEfhiZnXW+hDjnZcaVc="
  },
  "110,-104": {
    "SourceVersionHash": "xbEpX//NF1QAd+wV9rs7hoKC4Ic=",
    "VersionHash": "fCZfGZKapEfhiZnXW+hDjnZcaVc="
  },
  "112,-105": {
    "SourceVersionHash": "I8aToo+SQcdBh2GHRwH3xqeuTxY=",
    "VersionHash": "fCZfGZKapEfhiZnXW+hDjnZcaVc="
  },
  "112,-108": {
    "SourceVersionHash": "I8aToo+SQcdBh2GHRwH3xqeuTxY=",
    "VersionHash": "akP82J6Ho4Tno7G+29eZpzSKmG4="
  },
  "112,-109": {
    "SourceVersionHash": "I8aToo+SQcdBh2GHRwH3xqeuTxY=",
    "VersionHash": "akP82J6Ho4Tno7G+29eZpzSKmG4="
  },
  "112,-110": {
    "SourceVersionHash": "I8aToo+SQcdBh2GHRwH3xqeuTxY=",
    "VersionHash": "akP82J6Ho4Tno7G+29eZpzSKmG4="
  },
  "112,-107": {
    "SourceVersionHash": "I8aToo+SQcdBh2GHRwH3xqeuTxY=",
    "VersionHash": "akP82J6Ho4Tno7G+29eZpzSKmG4="
  },
  "112,-106": {
    "SourceVersionHash": "I8aToo+SQcdBh2GHRwH3xqeuTxY=",
    "VersionHash": "BM+xkRMY/esa3ZR+rHkp4pGllYw="
  },
  "113,-110": {
    "SourceVersionHash": "I8aToo+SQcdBh2GHRwH3xqeuTxY=",
    "VersionHash": "BM+xkRMY/esa3ZR+rHkp4pGllYw="
  },
  "114,-110": {
    "SourceVersionHash": "I8aToo+SQcdBh2GHRwH3xqeuTxY=",
    "VersionHash": "BM+xkRMY/esa3ZR+rHkp4pGllYw="
  },
  "116,-110": {
    "SourceVersionHash": "I8aToo+SQcdBh2GHRwH3xqeuTxY=",
    "VersionHash": "BM+xkRMY/esa3ZR+rHkp4pGllYw="
  },
  "118,-110": {
    "SourceVersionHash": "I8aToo+SQcdBh2GHRwH3xqeuTxY=",
    "VersionHash": "BM+xkRMY/esa3ZR+rHkp4pGllYw="
  },
  "115,-110": {
    "SourceVersionHash": "I8aToo+SQcdBh2GHRwH3xqeuTxY=",
    "VersionHash": "BM+xkRMY/esa3ZR+rHkp4pGllYw="
  },
  "119,-110": {
    "SourceVersionHash": "I8aToo+SQcdBh2GHRwH3xqeuTxY=",
    "VersionHash": "BM+xkRMY/esa3ZR+rHkp4pGllYw="
  },
  "113,-109": {
    "SourceVersionHash": "I8aToo+SQcdBh2GHRwH3xqeuTxY=",
    "VersionHash": "BM+xkRMY/esa3ZR+rHkp4pGllYw="
  },
  "117,-110": {
    "SourceVersionHash": "I8aToo+SQcdBh2GHRwH3xqeuTxY=",
    "VersionHash": "BM+xkRMY/esa3ZR+rHkp4pGllYw="
  },
  "114,-109": {
    "SourceVersionHash": "I8aToo+SQcdBh2GHRwH3xqeuTxY=",
    "VersionHash": "BM+xkRMY/esa3ZR+rHkp4pGllYw="
  },
  "115,-109": {
    "SourceVersionHash": "I8aToo+SQcdBh2GHRwH3xqeuTxY=",
    "VersionHash": "BM+xkRMY/esa3ZR+rHkp4pGllYw="
  },
  "113,-108": {
    "SourceVersionHash": "I8aToo+SQcdBh2GHRwH3xqeuTxY=",
    "VersionHash": "e3SwLp342AAhVs+pnIjVx4aT8WI="
  },
  "116,-109": {
    "SourceVersionHash": "I8aToo+SQcdBh2GHRwH3xqeuTxY=",
    "VersionHash": "e3SwLp342AAhVs+pnIjVx4aT8WI="
  },
  "117,-109": {
    "SourceVersionHash": "I8aToo+SQcdBh2GHRwH3xqeuTxY=",
    "VersionHash": "e3SwLp342AAhVs+pnIjVx4aT8WI="
  },
  "119,-109": {
    "SourceVersionHash": "I8aToo+SQcdBh2GHRwH3xqeuTxY=",
    "VersionHash": "e3SwLp342AAhVs+pnIjVx4aT8WI="
  },
  "114,-108": {
    "SourceVersionHash": "I8aToo+SQcdBh2GHRwH3xqeuTxY=",
    "VersionHash": "e3SwLp342AAhVs+pnIjVx4aT8WI="
  },
  "118,-109": {
    "SourceVersionHash": "I8aToo+SQcdBh2GHRwH3xqeuTxY=",
    "VersionHash": "e3SwLp342AAhVs+pnIjVx4aT8WI="
  },
  "116,-108": {
    "SourceVersionHash": "I8aToo+SQcdBh2GHRwH3xqeuTxY=",
    "VersionHash": "e3SwLp342AAhVs+pnIjVx4aT8WI="
  },
  "114,-107": {
    "SourceVersionHash": "I8aToo+SQcdBh2GHRwH3xqeuTxY=",
    "VersionHash": "e3SwLp342AAhVs+pnIjVx4aT8WI="
  },
  "115,-108": {
    "SourceVersionHash": "I8aToo+SQcdBh2GHRwH3xqeuTxY=",
    "VersionHash": "e3SwLp342AAhVs+pnIjVx4aT8WI="
  },
  "113,-107": {
    "SourceVersionHash": "I8aToo+SQcdBh2GHRwH3xqeuTxY=",
    "VersionHash": "e3SwLp342AAhVs+pnIjVx4aT8WI="
  },
  "119,-108": {
    "SourceVersionHash": "I8aToo+SQcdBh2GHRwH3xqeuTxY=",
    "VersionHash": "e3SwLp342AAhVs+pnIjVx4aT8WI="
  },
  "118,-108": {
    "SourceVersionHash": "I8aToo+SQcdBh2GHRwH3xqeuTxY=",
    "VersionHash": "e3SwLp342AAhVs+pnIjVx4aT8WI="
  },
  "118,-107": {
    "SourceVersionHash": "I8aToo+SQcdBh2GHRwH3xqeuTxY=",
    "VersionHash": "e3SwLp342AAhVs+pnIjVx4aT8WI="
  },
  "115,-107": {
    "SourceVersionHash": "I8aToo+SQcdBh2GHRwH3xqeuTxY=",
    "VersionHash": "e3SwLp342AAhVs+pnIjVx4aT8WI="
  },
  "117,-108": {
    "SourceVersionHash": "I8aToo+SQcdBh2GHRwH3xqeuTxY=",
    "VersionHash": "e3SwLp342AAhVs+pnIjVx4aT8WI="
  },
  "116,-107": {
    "SourceVersionHash": "I8aToo+SQcdBh2GHRwH3xqeuTxY=",
    "VersionHash": "e3SwLp342AAhVs+pnIjVx4aT8WI="
  },
  "113,-106": {
    "SourceVersionHash": "I8aToo+SQcdBh2GHRwH3xqeuTxY=",
    "VersionHash": "e3SwLp342AAhVs+pnIjVx4aT8WI="
  },
  "119,-107": {
    "SourceVersionHash": "I8aToo+SQcdBh2GHRwH3xqeuTxY=",
    "VersionHash": "e3SwLp342AAhVs+pnIjVx4aT8WI="
  },
  "117,-107": {
    "SourceVersionHash": "I8aToo+SQcdBh2GHRwH3xqeuTxY=",
    "VersionHash": "e3SwLp342AAhVs+pnIjVx4aT8WI="
  },
  "114,-106": {
    "SourceVersionHash": "I8aToo+SQcdBh2GHRwH3xqeuTxY=",
    "VersionHash": "e3SwLp342AAhVs+pnIjVx4aT8WI="
  },
  "115,-106": {
    "SourceVersionHash": "I8aToo+SQcdBh2GHRwH3xqeuTxY=",
    "VersionHash": "e3SwLp342AAhVs+pnIjVx4aT8WI="
  },
  "116,-106": {
    "SourceVersionHash": "I8aToo+SQcdBh2GHRwH3xqeuTxY=",
    "VersionHash": "e3SwLp342AAhVs+pnIjVx4aT8WI="
  },
  "117,-106": {
    "SourceVersionHash": "I8aToo+SQcdBh2GHRwH3xqeuTxY=",
    "VersionHash": "e3SwLp342AAhVs+pnIjVx4aT8WI="
  },
  "118,-106": {
    "SourceVersionHash": "I8aToo+SQcdBh2GHRwH3xqeuTxY=",
    "VersionHash": "e3SwLp342AAhVs+pnIjVx4aT8WI="
  },
  "119,-106": {
    "SourceVersionHash": "I8aToo+SQcdBh2GHRwH3xqeuTxY=",
    "VersionHash": "e3SwLp342AAhVs+pnIjVx4aT8WI="
  },
  "113,-105": {
    "SourceVersionHash": "I8aToo+SQcdBh2GHRwH3xqeuTxY=",
    "VersionHash": "e3SwLp342AAhVs+pnIjVx4aT8WI="
  },
  "115,-105": {
    "SourceVersionHash": "I8aToo+SQcdBh2GHRwH3xqeuTxY=",
    "VersionHash": "e3SwLp342AAhVs+pnIjVx4aT8WI="
  },
  "116,-105": {
    "SourceVersionHash": "I8aToo+SQcdBh2GHRwH3xqeuTxY=",
    "VersionHash": "e3SwLp342AAhVs+pnIjVx4aT8WI="
  },
  "117,-105": {
    "SourceVersionHash": "I8aToo+SQcdBh2GHRwH3xqeuTxY=",
    "VersionHash": "e3SwLp342AAhVs+pnIjVx4aT8WI="
  },
  "114,-105": {
    "SourceVersionHash": "I8aToo+SQcdBh2GHRwH3xqeuTxY=",
    "VersionHash": "e3SwLp342AAhVs+pnIjVx4aT8WI="
  },
  "118,-105": {
    "SourceVersionHash": "I8aToo+SQcdBh2GHRwH3xqeuTxY=",
    "VersionHash": "Yv2qwWmiBwvUrkzhdn1O4xol9RQ="
  },
  "119,-105": {
    "SourceVersionHash": "I8aToo+SQcdBh2GHRwH3xqeuTxY=",
    "VersionHash": "Yv2qwWmiBwvUrkzhdn1O4xol9RQ="
  }
}