{
  "125,-87": {
    "SourceVersionHash": "xbEpX//NF1QAd+wV9rs7hoKC4Ic=",
    "VersionHash": "B794MsXvCnUiwhHDEmq+cEQt1Ec="
  },
  "124,-85": {
    "SourceVersionHash": "xbEpX//NF1QAd+wV9rs7hoKC4Ic=",
    "VersionHash": "B794MsXvCnUiwhHDEmq+cEQt1Ec="
  },
  "126,-88": {
    "SourceVersionHash": "xbEpX//NF1QAd+wV9rs7hoKC4Ic=",
    "VersionHash": "B794MsXvCnUiwhHDEmq+cEQt1Ec="
  },
  "124,-88": {
    "SourceVersionHash": "xbEpX//NF1QAd+wV9rs7hoKC4Ic=",
    "VersionHash": "B794MsXvCnUiwhHDEmq+cEQt1Ec="
  },
  "125,-88": {
    "SourceVersionHash": "xbEpX//NF1QAd+wV9rs7hoKC4Ic=",
    "VersionHash": "B794MsXvCnUiwhHDEmq+cEQt1Ec="
  },
  "127,-85": {
    "SourceVersionHash": "xbEpX//NF1QAd+wV9rs7hoKC4Ic=",
    "VersionHash": "B794MsXvCnUiwhHDEmq+cEQt1Ec="
  },
  "124,-87": {
    "SourceVersionHash": "xbEpX//NF1QAd+wV9rs7hoKC4Ic=",
    "VersionHash": "B794MsXvCnUiwhHDEmq+cEQt1Ec="
  },
  "127,-87": {
    "SourceVersionHash": "xbEpX//NF1QAd+wV9rs7hoKC4Ic=",
    "VersionHash": "B794MsXvCnUiwhHDEmq+cEQt1Ec="
  },
  "127,-86": {
    "SourceVersionHash": "xbEpX//NF1QAd+wV9rs7hoKC4Ic=",
    "VersionHash": "B794MsXvCnUiwhHDEmq+cEQt1Ec="
  },
  "126,-86": {
    "SourceVersionHash": "xbEpX//NF1QAd+wV9rs7hoKC4Ic=",
    "VersionHash": "B794MsXvCnUiwhHDEmq+cEQt1Ec="
  },
  "125,-85": {
    "SourceVersionHash": "xbEpX//NF1QAd+wV9rs7hoKC4Ic=",
    "VersionHash": "B794MsXvCnUiwhHDEmq+cEQt1Ec="
  },
  "124,-86": {
    "SourceVersionHash": "xbEpX//NF1QAd+wV9rs7hoKC4Ic=",
    "VersionHash": "B794MsXvCnUiwhHDEmq+cEQt1Ec="
  },
  "125,-86": {
    "SourceVersionHash": "xbEpX//NF1QAd+wV9rs7hoKC4Ic=",
    "VersionHash": "B794MsXvCnUiwhHDEmq+cEQt1Ec="
  },
  "126,-85": {
    "SourceVersionHash": "xbEpX//NF1QAd+wV9rs7hoKC4Ic=",
    "VersionHash": "B794MsXvCnUiwhHDEmq+cEQt1Ec="
  },
  "126,-87": {
    "SourceVersionHash": "xbEpX//NF1QAd+wV9rs7hoKC4Ic=",
    "VersionHash": "B794MsXvCnUiwhHDEmq+cEQt1Ec="
  },
  "127,-88": {
    "SourceVersionHash": "xbEpX//NF1QAd+wV9rs7hoKC4Ic=",
    "VersionHash": "B794MsXvCnUiwhHDEmq+cEQt1Ec="
  }
}