{
  "-230,-31": {
    "SourceVersionHash": "CdjE2eyJERitiQV+zeTZA6R7uDM=",
    "VersionHash": "BtoT5AcJLJ+/Z9x3waRGijxrGng="
  },
  "-228,-31": {
    "SourceVersionHash": "CdjE2eyJERitiQV+zeTZA6R7uDM=",
    "VersionHash": "BtoT5AcJLJ+/Z9x3waRGijxrGng="
  },
  "-227,-31": {
    "SourceVersionHash": "CdjE2eyJERitiQV+zeTZA6R7uDM=",
    "VersionHash": "BtoT5AcJLJ+/Z9x3waRGijxrGng="
  },
  "-229,-31": {
    "SourceVersionHash": "CdjE2eyJERitiQV+zeTZA6R7uDM=",
    "VersionHash": "BtoT5AcJLJ+/Z9x3waRGijxrGng="
  },
  "-226,-31": {
    "SourceVersionHash": "CdjE2eyJERitiQV+zeTZA6R7uDM=",
    "VersionHash": "BtoT5AcJLJ+/Z9x3waRGijxrGng="
  },
  "-230,-32": {
    "SourceVersionHash": "CdjE2eyJERitiQV+zeTZA6R7uDM=",
    "VersionHash": "BtoT5AcJLJ+/Z9x3waRGijxrGng="
  },
  "-229,-32": {
    "SourceVersionHash": "CdjE2eyJERitiQV+zeTZA6R7uDM=",
    "VersionHash": "BtoT5AcJLJ+/Z9x3waRGijxrGng="
  },
  "-227,-32": {
    "SourceVersionHash": "CdjE2eyJERitiQV+zeTZA6R7uDM=",
    "VersionHash": "BtoT5AcJLJ+/Z9x3waRGijxrGng="
  },
  "-226,-32": {
    "SourceVersionHash": "CdjE2eyJERitiQV+zeTZA6R7uDM=",
    "VersionHash": "BtoT5AcJLJ+/Z9x3waRGijxrGng="
  },
  "-228,-32": {
    "SourceVersionHash": "CdjE2eyJERitiQV+zeTZA6R7uDM=",
    "VersionHash": "BtoT5AcJLJ+/Z9x3waRGijxrGng="
  },
  "-225,-32": {
    "SourceVersionHash": "CdjE2eyJERitiQV+zeTZA6R7uDM=",
    "VersionHash": "BtoT5AcJLJ+/Z9x3waRGijxrGng="
  },
  "-224,-32": {
    "SourceVersionHash": "xbEpX//NF1QAd+wV9rs7hoKC4Ic=",
    "VersionHash": "BtoT5AcJLJ+/Z9x3waRGijxrGng="
  },
  "-225,-31": {
    "SourceVersionHash": "CdjE2eyJERitiQV+zeTZA6R7uDM=",
    "VersionHash": "BtoT5AcJLJ+/Z9x3waRGijxrGng="
  },
  "-224,-31": {
    "SourceVersionHash": "xbEpX//NF1QAd+wV9rs7hoKC4Ic=",
    "VersionHash": "BtoT5AcJLJ+/Z9x3waRGijxrGng="
  },
  "-223,-32": {
    "SourceVersionHash": "xbEpX//NF1QAd+wV9rs7hoKC4Ic=",
    "VersionHash": "tN9LvfiKgwUEScG/THFNhB+estM="
  },
  "-222,-32": {
    "SourceVersionHash": "xbEpX//NF1QAd+wV9rs7hoKC4Ic=",
    "VersionHash": "K1BuxQ4zZT7GeAJCX3sUkl6yW2g="
  },
  "-221,-32": {
    "SourceVersionHash": "xbEpX//NF1QAd+wV9rs7hoKC4Ic=",
    "VersionHash": "K1BuxQ4zZT7GeAJCX3sUkl6yW2g="
  },
  "-223,-31": {
    "SourceVersionHash": "xbEpX//NF1QAd+wV9rs7hoKC4Ic=",
    "VersionHash": "K1BuxQ4zZT7GeAJCX3sUkl6yW2g="
  },
  "-222,-31": {
    "SourceVersionHash": "xbEpX//NF1QAd+wV9rs7hoKC4Ic=",
    "VersionHash": "K1BuxQ4zZT7GeAJCX3sUkl6yW2g="
  },
  "-221,-31": {
    "SourceVersionHash": "xbEpX//NF1QAd+wV9rs7hoKC4Ic=",
    "VersionHash": "K1BuxQ4zZT7GeAJCX3sUkl6yW2g="
  }
}