{
  "93,-28": {
    "SourceVersionHash": "xbEpX//NF1QAd+wV9rs7hoKC4Ic=",
    "VersionHash": "djLShe79fAfCb6xh31Nt/p8d7XI="
  },
  "92,-27": {
    "SourceVersionHash": "xbEpX//NF1QAd+wV9rs7hoKC4Ic=",
    "VersionHash": "djLShe79fAfCb6xh31Nt/p8d7XI="
  },
  "94,-28": {
    "SourceVersionHash": "xbEpX//NF1QAd+wV9rs7hoKC4Ic=",
    "VersionHash": "djLShe79fAfCb6xh31Nt/p8d7XI="
  },
  "95,-28": {
    "SourceVersionHash": "xbEpX//NF1QAd+wV9rs7hoKC4Ic=",
    "VersionHash": "djLShe79fAfCb6xh31Nt/p8d7XI="
  },
  "92,-28": {
    "SourceVersionHash": "xbEpX//NF1QAd+wV9rs7hoKC4Ic=",
    "VersionHash": "djLShe79fAfCb6xh31Nt/p8d7XI="
  },
  "93,-27": {
    "SourceVersionHash": "xbEpX//NF1QAd+wV9rs7hoKC4Ic=",
    "VersionHash": "djLShe79fAfCb6xh31Nt/p8d7XI="
  },
  "92,-25": {
    "SourceVersionHash": "xbEpX//NF1QAd+wV9rs7hoKC4Ic=",
    "VersionHash": "djLShe79fAfCb6xh31Nt/p8d7XI="
  },
  "94,-27": {
    "SourceVersionHash": "xbEpX//NF1QAd+wV9rs7hoKC4Ic=",
    "VersionHash": "djLShe79fAfCb6xh31Nt/p8d7XI="
  },
  "93,-26": {
    "SourceVersionHash": "xbEpX//NF1QAd+wV9rs7hoKC4Ic=",
    "VersionHash": "djLShe79fAfCb6xh31Nt/p8d7XI="
  },
  "95,-27": {
    "SourceVersionHash": "xbEpX//NF1QAd+wV9rs7hoKC4Ic=",
    "VersionHash": "djLShe79fAfCb6xh31Nt/p8d7XI="
  },
  "92,-26": {
    "SourceVersionHash": "xbEpX//NF1QAd+wV9rs7hoKC4Ic=",
    "VersionHash": "djLShe79fAfCb6xh31Nt/p8d7XI="
  },
  "94,-26": {
    "SourceVersionHash": "xbEpX//NF1QAd+wV9rs7hoKC4Ic=",
    "VersionHash": "djLShe79fAfCb6xh31Nt/p8d7XI="
  },
  "94,-25": {
    "SourceVersionHash": "xbEpX//NF1QAd+wV9rs7hoKC4Ic=",
    "VersionHash": "djLShe79fAfCb6xh31Nt/p8d7XI="
  },
  "95,-26": {
    "SourceVersionHash": "xbEpX//NF1QAd+wV9rs7hoKC4Ic=",
    "VersionHash": "djLShe79fAfCb6xh31Nt/p8d7XI="
  },
  "95,-25": {
    "SourceVersionHash": "xbEpX//NF1QAd+wV9rs7hoKC4Ic=",
    "VersionHash": "djLShe79fAfCb6xh31Nt/p8d7XI="
  },
  "93,-25": {
    "SourceVersionHash": "xbEpX//NF1QAd+wV9rs7hoKC4Ic=",
    "VersionHash": "djLShe79fAfCb6xh31Nt/p8d7XI="
  }
}